[{"AREAC":[{"name":"-2","data":[397]},{"name":"0","data":[182]},{"name":"1","data":[1451]}]},{"STNUM":[{"name":"1","data":[382]},{"name":"2","data":[143]},{"name":"3","data":[449]},{"name":"4","data":[298]},{"name":"5","data":[362]},{"name":"6","data":[396]}]},{"PGNUM":[{"name":"1","data":[83]},{"name":"10","data":[82]},{"name":"11","data":[75]},{"name":"12","data":[74]},{"name":"13","data":[74]},{"name":"14","data":[75]},{"name":"15","data":[62]},{"name":"16","data":[75]},{"name":"17","data":[75]},{"name":"18","data":[71]},{"name":"19","data":[73]},{"name":"2","data":[85]},{"name":"20","data":[75]},{"name":"21","data":[66]},{"name":"22","data":[60]},{"name":"23","data":[60]},{"name":"24","data":[59]},{"name":"25","data":[59]},{"name":"26","data":[54]},{"name":"27","data":[29]},{"name":"28","data":[15]},{"name":"29","data":[15]},{"name":"3","data":[83]},{"name":"30","data":[14]},{"name":"4","data":[90]},{"name":"5","data":[89]},{"name":"6","data":[90]},{"name":"7","data":[89]},{"name":"8","data":[89]},{"name":"9","data":[90]}]},{"LGNUM":[{"name":"1","data":[139]},{"name":"10","data":[135]},{"name":"11","data":[133]},{"name":"12","data":[131]},{"name":"13","data":[132]},{"name":"14","data":[131]},{"name":"15","data":[131]},{"name":"2","data":[140]},{"name":"3","data":[137]},{"name":"4","data":[138]},{"name":"5","data":[137]},{"name":"6","data":[138]},{"name":"7","data":[137]},{"name":"8","data":[136]},{"name":"9","data":[135]}]},{"DTCON":[{"name":"01-APR-1997","data":[2]},{"name":"01-APR-1998","data":[5]},{"name":"01-AUG-1997","data":[5]},{"name":"01-DEC-1997","data":[4]},{"name":"01-DEC-1998","data":[3]},{"name":"01-DEC-1999","data":[1]},{"name":"01-FEB-1998","data":[1]},{"name":"01-FEB-1999","data":[7]},{"name":"01-JUL-1997","data":[3]},{"name":"01-JUL-1998","data":[1]},{"name":"01-JUN-1998","data":[1]},{"name":"01-MAR-1999","data":[2]},{"name":"01-MAR-2000","data":[1]},{"name":"01-MAY-1997","data":[4]},{"name":"01-MAY-1998","data":[3]},{"name":"01-OCT-1996","data":[1]},{"name":"01-OCT-1997","data":[3]},{"name":"01-OCT-1998","data":[3]},{"name":"01-OCT-1999","data":[1]},{"name":"01-SEP-1998","data":[2]},{"name":"02-APR-1997","data":[1]},{"name":"02-APR-1998","data":[7]},{"name":"02-APR-1999","data":[1]},{"name":"02-AUG-1998","data":[1]},{"name":"02-AUG-1999","data":[1]},{"name":"02-DEC-1996","data":[5]},{"name":"02-DEC-1997","data":[1]},{"name":"02-DEC-1998","data":[1]},{"name":"02-FEB-1998","data":[2]},{"name":"02-FEB-1999","data":[7]},{"name":"02-FEB-2000","data":[2]},{"name":"02-JAN-1997","data":[6]},{"name":"02-JAN-1998","data":[1]},{"name":"02-JUL-1997","data":[2]},{"name":"02-JUL-1998","data":[1]},{"name":"02-JUN-1997","data":[2]},{"name":"02-JUN-1998","data":[6]},{"name":"02-JUN-1999","data":[2]},{"name":"02-MAR-1998","data":[4]},{"name":"02-MAR-1999","data":[5]},{"name":"02-MAY-1997","data":[2]},{"name":"02-NOV-1998","data":[2]},{"name":"02-OCT-1996","data":[5]},{"name":"02-OCT-1997","data":[5]},{"name":"02-SEP-1997","data":[5]},{"name":"03-APR-1997","data":[2]},{"name":"03-APR-1998","data":[5]},{"name":"03-AUG-1998","data":[3]},{"name":"03-DEC-1996","data":[2]},{"name":"03-DEC-1997","data":[2]},{"name":"03-DEC-1998","data":[4]},{"name":"03-FEB-1997","data":[5]},{"name":"03-FEB-1998","data":[4]},{"name":"03-FEB-1999","data":[4]},{"name":"03-FEB-2000","data":[1]},{"name":"03-JAN-1997","data":[3]},{"name":"03-JUL-1997","data":[1]},{"name":"03-JUL-1998","data":[1]},{"name":"03-JUN-1997","data":[2]},{"name":"03-JUN-1998","data":[3]},{"name":"03-JUN-1999","data":[1]},{"name":"03-MAR-1997","data":[2]},{"name":"03-MAR-1998","data":[4]},{"name":"03-MAR-2000","data":[2]},{"name":"03-MAY-1997","data":[1]},{"name":"03-MAY-1999","data":[4]},{"name":"03-NOV-1997","data":[4]},{"name":"03-NOV-1998","data":[5]},{"name":"03-OCT-1997","data":[3]},{"name":"03-SEP-1997","data":[2]},{"name":"03-SEP-1998","data":[4]},{"name":"04-APR-1997","data":[16]},{"name":"04-APR-1998","data":[2]},{"name":"04-AUG-1998","data":[4]},{"name":"04-DEC-1996","data":[1]},{"name":"04-DEC-1997","data":[2]},{"name":"04-DEC-1998","data":[4]},{"name":"04-FEB-1997","data":[2]},{"name":"04-FEB-1998","data":[4]},{"name":"04-FEB-1999","data":[3]},{"name":"04-JAN-1999","data":[4]},{"name":"04-JUN-1997","data":[2]},{"name":"04-JUN-1998","data":[1]},{"name":"04-JUN-1999","data":[1]},{"name":"04-MAR-1997","data":[2]},{"name":"04-MAR-1998","data":[6]},{"name":"04-MAR-1999","data":[4]},{"name":"04-MAY-1998","data":[5]},{"name":"04-NOV-1997","data":[2]},{"name":"04-NOV-1998","data":[7]},{"name":"04-OCT-1996","data":[1]},{"name":"04-SEP-1997","data":[2]},{"name":"05-APR-1999","data":[2]},{"name":"05-AUG-1997","data":[4]},{"name":"05-AUG-1998","data":[1]},{"name":"05-DEC-1996","data":[3]},{"name":"05-FEB-1997","data":[3]},{"name":"05-FEB-1998","data":[6]},{"name":"05-FEB-1999","data":[3]},{"name":"05-JAN-1998","data":[5]},{"name":"05-JAN-1999","data":[3]},{"name":"05-JUL-1998","data":[1]},{"name":"05-JUN-1997","data":[3]},{"name":"05-JUN-1998","data":[7]},{"name":"05-MAR-1997","data":[7]},{"name":"05-MAR-1998","data":[8]},{"name":"05-MAR-1999","data":[7]},{"name":"05-MAY-1997","data":[2]},{"name":"05-MAY-1998","data":[1]},{"name":"05-MAY-1999","data":[3]},{"name":"05-NOV-1997","data":[2]},{"name":"05-NOV-1999","data":[1]},{"name":"05-OCT-1998","data":[3]},{"name":"05-SEP-1997","data":[2]},{"name":"06-APR-1998","data":[4]},{"name":"06-AUG-1997","data":[4]},{"name":"06-AUG-1998","data":[1]},{"name":"06-DEC-1996","data":[9]},{"name":"06-DEC-1997","data":[1]},{"name":"06-FEB-1997","data":[1]},{"name":"06-FEB-1998","data":[7]},{"name":"06-JAN-1997","data":[8]},{"name":"06-JAN-1998","data":[5]},{"name":"06-JAN-1999","data":[6]},{"name":"06-JUL-1998","data":[4]},{"name":"06-JUL-1999","data":[1]},{"name":"06-JUN-1997","data":[2]},{"name":"06-MAR-1997","data":[2]},{"name":"06-MAR-1998","data":[3]},{"name":"06-MAY-1997","data":[3]},{"name":"06-MAY-1998","data":[6]},{"name":"06-MAY-1999","data":[2]},{"name":"06-NOV-1996","data":[1]},{"name":"06-OCT-1997","data":[8]},{"name":"06-OCT-1998","data":[3]},{"name":"06-OCT-1999","data":[1]},{"name":"07-APR-1998","data":[2]},{"name":"07-APR-1999","data":[3]},{"name":"07-AUG-1997","data":[4]},{"name":"07-AUG-1998","data":[2]},{"name":"07-DEC-1997","data":[2]},{"name":"07-DEC-1998","data":[2]},{"name":"07-DEC-1999","data":[2]},{"name":"07-FEB-1997","data":[2]},{"name":"07-FEB-2000","data":[2]},{"name":"07-JAN-1997","data":[1]},{"name":"07-JAN-1998","data":[4]},{"name":"07-JAN-1999","data":[4]},{"name":"07-JUL-1997","data":[1]},{"name":"07-JUL-1998","data":[2]},{"name":"07-JUL-1999","data":[4]},{"name":"07-JUN-1999","data":[1]},{"name":"07-MAR-1997","data":[3]},{"name":"07-MAR-1998","data":[1]},{"name":"07-MAR-2000","data":[2]},{"name":"07-MAY-1997","data":[6]},{"name":"07-MAY-1998","data":[2]},{"name":"07-MAY-1999","data":[3]},{"name":"07-NOV-1996","data":[3]},{"name":"07-NOV-1997","data":[2]},{"name":"07-NOV-1998","data":[1]},{"name":"07-OCT-1996","data":[2]},{"name":"07-OCT-1997","data":[2]},{"name":"07-OCT-1998","data":[5]},{"name":"07-SEP-1999","data":[3]},{"name":"08-APR-1997","data":[2]},{"name":"08-APR-1998","data":[5]},{"name":"08-DEC-1997","data":[2]},{"name":"08-FEB-1997","data":[8]},{"name":"08-FEB-1998","data":[2]},{"name":"08-FEB-1999","data":[4]},{"name":"08-FEB-2000","data":[4]},{"name":"08-JAN-1997","data":[4]},{"name":"08-JAN-1998","data":[3]},{"name":"08-JAN-1999","data":[7]},{"name":"08-JUL-1997","data":[3]},{"name":"08-JUL-1998","data":[5]},{"name":"08-JUN-1998","data":[3]},{"name":"08-MAR-1998","data":[1]},{"name":"08-MAR-1999","data":[3]},{"name":"08-MAR-2000","data":[2]},{"name":"08-MAY-1997","data":[3]},{"name":"08-MAY-1998","data":[1]},{"name":"08-NOV-1996","data":[2]},{"name":"08-OCT-1997","data":[3]},{"name":"08-OCT-1998","data":[1]},{"name":"08-SEP-1997","data":[2]},{"name":"08-SEP-1998","data":[1]},{"name":"09-APR-1997","data":[2]},{"name":"09-APR-1998","data":[2]},{"name":"09-APR-1999","data":[1]},{"name":"09-DEC-1996","data":[4]},{"name":"09-DEC-1997","data":[6]},{"name":"09-DEC-1998","data":[3]},{"name":"09-DEC-1999","data":[1]},{"name":"09-FEB-1998","data":[7]},{"name":"09-FEB-1999","data":[2]},{"name":"09-FEB-2000","data":[2]},{"name":"09-JAN-1997","data":[2]},{"name":"09-JAN-1998","data":[2]},{"name":"09-JUL-1997","data":[4]},{"name":"09-JUL-1998","data":[5]},{"name":"09-JUL-1999","data":[1]},{"name":"09-JUN-1997","data":[2]},{"name":"09-JUN-1998","data":[3]},{"name":"09-MAR-1997","data":[1]},{"name":"09-MAR-1998","data":[4]},{"name":"09-MAR-1999","data":[8]},{"name":"09-MAY-1998","data":[1]},{"name":"09-NOV-1997","data":[1]},{"name":"09-NOV-1998","data":[4]},{"name":"09-NOV-1999","data":[1]},{"name":"09-OCT-1997","data":[4]},{"name":"09-OCT-1998","data":[2]},{"name":"09-SEP-1997","data":[4]},{"name":"09-SEP-1998","data":[2]},{"name":"09-SEP-1999","data":[1]},{"name":"10-APR-1997","data":[6]},{"name":"10-APR-1998","data":[3]},{"name":"10-AUG-1998","data":[2]},{"name":"10-AUG-1999","data":[1]},{"name":"10-DEC-1996","data":[5]},{"name":"10-DEC-1997","data":[9]},{"name":"10-DEC-1998","data":[1]},{"name":"10-FEB-1997","data":[2]},{"name":"10-FEB-1998","data":[6]},{"name":"10-FEB-1999","data":[1]},{"name":"10-FEB-2000","data":[1]},{"name":"10-JAN-1997","data":[3]},{"name":"10-JAN-1998","data":[1]},{"name":"10-JAN-2000","data":[3]},{"name":"10-JUL-1997","data":[4]},{"name":"10-JUL-1998","data":[2]},{"name":"10-JUN-1997","data":[2]},{"name":"10-JUN-1998","data":[6]},{"name":"10-JUN-1999","data":[3]},{"name":"10-MAR-1997","data":[7]},{"name":"10-MAR-1998","data":[1]},{"name":"10-MAR-1999","data":[2]},{"name":"10-MAR-2000","data":[1]},{"name":"10-MAY-1999","data":[3]},{"name":"10-NOV-1997","data":[6]},{"name":"10-NOV-1998","data":[5]},{"name":"10-OCT-1997","data":[4]},{"name":"10-SEP-1997","data":[4]},{"name":"10-SEP-1998","data":[3]},{"name":"10-SEP-1999","data":[1]},{"name":"11-APR-1997","data":[3]},{"name":"11-APR-1998","data":[1]},{"name":"11-APR-1999","data":[1]},{"name":"11-DEC-1997","data":[2]},{"name":"11-DEC-1998","data":[3]},{"name":"11-FEB-1997","data":[2]},{"name":"11-FEB-1998","data":[4]},{"name":"11-FEB-1999","data":[2]},{"name":"11-JAN-1999","data":[1]},{"name":"11-JUL-1997","data":[7]},{"name":"11-JUL-1998","data":[5]},{"name":"11-JUN-1997","data":[1]},{"name":"11-JUN-1998","data":[1]},{"name":"11-MAR-1997","data":[4]},{"name":"11-MAR-1998","data":[2]},{"name":"11-MAR-1999","data":[2]},{"name":"11-MAY-1998","data":[6]},{"name":"11-MAY-1999","data":[3]},{"name":"11-NOV-1998","data":[4]},{"name":"11-SEP-1997","data":[9]},{"name":"12-APR-1999","data":[1]},{"name":"12-AUG-1998","data":[2]},{"name":"12-AUG-1999","data":[2]},{"name":"12-DEC-1997","data":[4]},{"name":"12-FEB-1997","data":[2]},{"name":"12-FEB-1998","data":[5]},{"name":"12-FEB-1999","data":[4]},{"name":"12-JAN-1998","data":[2]},{"name":"12-JAN-1999","data":[2]},{"name":"12-JAN-2000","data":[4]},{"name":"12-JUL-1999","data":[1]},{"name":"12-JUN-1997","data":[1]},{"name":"12-JUN-1998","data":[2]},{"name":"12-MAR-1997","data":[6]},{"name":"12-MAR-1998","data":[2]},{"name":"12-MAR-1999","data":[1]},{"name":"12-MAY-1997","data":[3]},{"name":"12-MAY-1998","data":[4]},{"name":"12-NOV-1997","data":[2]},{"name":"12-NOV-1998","data":[1]},{"name":"12-OCT-1998","data":[4]},{"name":"12-SEP-1996","data":[2]},{"name":"12-SEP-1997","data":[4]},{"name":"13-APR-1998","data":[6]},{"name":"13-APR-1999","data":[1]},{"name":"13-AUG-1997","data":[4]},{"name":"13-AUG-1998","data":[1]},{"name":"13-DEC-1996","data":[2]},{"name":"13-FEB-1997","data":[2]},{"name":"13-JAN-1997","data":[1]},{"name":"13-JAN-1998","data":[4]},{"name":"13-JAN-1999","data":[2]},{"name":"13-JUL-1998","data":[1]},{"name":"13-JUN-1997","data":[2]},{"name":"13-MAR-1997","data":[4]},{"name":"13-MAR-1998","data":[1]},{"name":"13-MAR-2000","data":[2]},{"name":"13-MAY-1997","data":[4]},{"name":"13-MAY-1998","data":[6]},{"name":"13-NOV-1997","data":[3]},{"name":"13-NOV-1998","data":[5]},{"name":"13-OCT-1997","data":[2]},{"name":"13-OCT-1998","data":[3]},{"name":"14-APR-1998","data":[3]},{"name":"14-APR-1999","data":[1]},{"name":"14-AUG-1997","data":[2]},{"name":"14-AUG-1998","data":[1]},{"name":"14-DEC-1997","data":[1]},{"name":"14-DEC-1998","data":[1]},{"name":"14-DEC-1999","data":[3]},{"name":"14-FEB-1997","data":[1]},{"name":"14-JAN-1998","data":[3]},{"name":"14-JAN-1999","data":[3]},{"name":"14-JUL-1997","data":[6]},{"name":"14-JUL-1998","data":[4]},{"name":"14-MAR-1997","data":[1]},{"name":"14-MAR-1998","data":[2]},{"name":"14-MAY-1997","data":[1]},{"name":"14-MAY-1998","data":[1]},{"name":"14-MAY-1999","data":[4]},{"name":"14-NOV-1996","data":[1]},{"name":"14-NOV-1997","data":[1]},{"name":"14-OCT-1997","data":[5]},{"name":"14-OCT-1998","data":[1]},{"name":"14-OCT-1999","data":[1]},{"name":"14-SEP-1998","data":[2]},{"name":"15-APR-1997","data":[5]},{"name":"15-APR-1998","data":[5]},{"name":"15-AUG-1997","data":[4]},{"name":"15-DEC-1997","data":[3]},{"name":"15-DEC-1999","data":[2]},{"name":"15-FEB-1999","data":[7]},{"name":"15-FEB-2000","data":[2]},{"name":"15-JAN-1997","data":[1]},{"name":"15-JAN-1998","data":[2]},{"name":"15-JAN-1999","data":[3]},{"name":"15-JUL-1997","data":[3]},{"name":"15-JUL-1998","data":[5]},{"name":"15-JUN-1998","data":[4]},{"name":"15-JUN-1999","data":[1]},{"name":"15-MAR-1998","data":[2]},{"name":"15-MAR-1999","data":[8]},{"name":"15-MAY-1997","data":[1]},{"name":"15-MAY-1998","data":[2]},{"name":"15-NOV-1996","data":[1]},{"name":"15-NOV-1999","data":[3]},{"name":"15-OCT-1997","data":[3]},{"name":"15-OCT-1998","data":[4]},{"name":"15-SEP-1997","data":[9]},{"name":"15-SEP-1998","data":[2]},{"name":"16-APR-1997","data":[2]},{"name":"16-APR-1998","data":[5]},{"name":"16-APR-1999","data":[2]},{"name":"16-AUG-1999","data":[3]},{"name":"16-DEC-1996","data":[5]},{"name":"16-DEC-1997","data":[3]},{"name":"16-DEC-1998","data":[1]},{"name":"16-FEB-1998","data":[3]},{"name":"16-FEB-2000","data":[2]},{"name":"16-JAN-1997","data":[1]},{"name":"16-JAN-1998","data":[1]},{"name":"16-JUL-1997","data":[1]},{"name":"16-JUL-1998","data":[3]},{"name":"16-JUN-1998","data":[5]},{"name":"16-JUN-1999","data":[1]},{"name":"16-MAR-1998","data":[8]},{"name":"16-MAR-1999","data":[2]},{"name":"16-MAY-1997","data":[1]},{"name":"16-NOV-1998","data":[2]},{"name":"16-OCT-1997","data":[3]},{"name":"16-OCT-1998","data":[2]},{"name":"16-SEP-1996","data":[6]},{"name":"16-SEP-1998","data":[2]},{"name":"17-APR-1998","data":[1]},{"name":"17-AUG-1998","data":[1]},{"name":"17-DEC-1996","data":[10]},{"name":"17-DEC-1997","data":[5]},{"name":"17-FEB-1997","data":[2]},{"name":"17-FEB-1998","data":[4]},{"name":"17-FEB-1999","data":[5]},{"name":"17-FEB-2000","data":[1]},{"name":"17-JUL-1997","data":[3]},{"name":"17-JUL-1998","data":[3]},{"name":"17-JUN-1997","data":[2]},{"name":"17-JUN-1998","data":[5]},{"name":"17-JUN-1999","data":[1]},{"name":"17-MAR-1997","data":[4]},{"name":"17-MAR-1998","data":[2]},{"name":"17-MAR-1999","data":[5]},{"name":"17-MAR-2000","data":[1]},{"name":"17-MAY-1999","data":[4]},{"name":"17-NOV-1997","data":[2]},{"name":"17-OCT-1997","data":[5]},{"name":"17-SEP-1996","data":[2]},{"name":"17-SEP-1997","data":[5]},{"name":"17-SEP-1998","data":[2]},{"name":"18-AUG-1997","data":[10]},{"name":"18-AUG-1998","data":[1]},{"name":"18-DEC-1996","data":[2]},{"name":"18-DEC-1997","data":[4]},{"name":"18-DEC-1998","data":[5]},{"name":"18-FEB-1997","data":[5]},{"name":"18-FEB-1998","data":[5]},{"name":"18-FEB-1999","data":[3]},{"name":"18-JAN-1999","data":[1]},{"name":"18-JUL-1997","data":[2]},{"name":"18-JUN-1997","data":[4]},{"name":"18-JUN-1998","data":[2]},{"name":"18-MAR-1997","data":[8]},{"name":"18-MAR-1998","data":[5]},{"name":"18-MAR-1999","data":[5]},{"name":"18-MAY-1998","data":[4]},{"name":"18-NOV-1996","data":[4]},{"name":"18-NOV-1998","data":[1]},{"name":"18-OCT-1998","data":[1]},{"name":"18-SEP-1996","data":[5]},{"name":"18-SEP-1997","data":[3]},{"name":"18-SEP-1998","data":[4]},{"name":"19-AUG-1997","data":[6]},{"name":"19-DEC-1996","data":[4]},{"name":"19-DEC-1997","data":[3]},{"name":"19-DEC-1998","data":[3]},{"name":"19-FEB-1998","data":[3]},{"name":"19-FEB-1999","data":[2]},{"name":"19-JAN-1998","data":[2]},{"name":"19-JAN-1999","data":[4]},{"name":"19-JAN-2000","data":[1]},{"name":"19-JUN-1997","data":[4]},{"name":"19-MAR-1997","data":[11]},{"name":"19-MAR-1998","data":[2]},{"name":"19-MAY-1997","data":[1]},{"name":"19-MAY-1998","data":[3]},{"name":"19-NOV-1997","data":[3]},{"name":"19-NOV-1998","data":[1]},{"name":"19-OCT-1998","data":[1]},{"name":"19-SEP-1996","data":[3]},{"name":"19-SEP-1997","data":[5]},{"name":"19-SEP-1998","data":[2]},{"name":"20-APR-1997","data":[1]},{"name":"20-APR-1998","data":[2]},{"name":"20-APR-1999","data":[1]},{"name":"20-AUG-1997","data":[6]},{"name":"20-AUG-1998","data":[1]},{"name":"20-DEC-1996","data":[5]},{"name":"20-FEB-1997","data":[2]},{"name":"20-FEB-1998","data":[1]},{"name":"20-JAN-1998","data":[7]},{"name":"20-JAN-1999","data":[5]},{"name":"20-JAN-2000","data":[1]},{"name":"20-JUL-1997","data":[1]},{"name":"20-JUL-1998","data":[6]},{"name":"20-JUL-1999","data":[1]},{"name":"20-JUN-1997","data":[4]},{"name":"20-MAR-1997","data":[5]},{"name":"20-MAR-1998","data":[3]},{"name":"20-MAY-1997","data":[3]},{"name":"20-MAY-1998","data":[3]},{"name":"20-NOV-1997","data":[1]},{"name":"20-OCT-1997","data":[7]},{"name":"20-OCT-1998","data":[5]},{"name":"20-SEP-1996","data":[5]},{"name":"20-SEP-1999","data":[1]},{"name":"21-APR-1997","data":[2]},{"name":"21-APR-1999","data":[2]},{"name":"21-AUG-1997","data":[2]},{"name":"21-DEC-1998","data":[1]},{"name":"21-FEB-1997","data":[1]},{"name":"21-JAN-1998","data":[4]},{"name":"21-JAN-1999","data":[6]},{"name":"21-JUL-1997","data":[8]},{"name":"21-JUL-1998","data":[4]},{"name":"21-JUL-1999","data":[1]},{"name":"21-JUN-1998","data":[1]},{"name":"21-MAR-1997","data":[2]},{"name":"21-MAY-1997","data":[3]},{"name":"21-MAY-1998","data":[2]},{"name":"21-NOV-1996","data":[1]},{"name":"21-NOV-1997","data":[1]},{"name":"21-OCT-1997","data":[5]},{"name":"21-OCT-1998","data":[2]},{"name":"21-SEP-1998","data":[3]},{"name":"22-APR-1997","data":[3]},{"name":"22-APR-1998","data":[1]},{"name":"22-APR-1999","data":[1]},{"name":"22-AUG-1997","data":[2]},{"name":"22-DEC-1997","data":[6]},{"name":"22-DEC-1998","data":[1]},{"name":"22-FEB-1998","data":[1]},{"name":"22-FEB-1999","data":[5]},{"name":"22-FEB-2000","data":[2]},{"name":"22-JAN-1997","data":[2]},{"name":"22-JAN-1998","data":[2]},{"name":"22-JAN-1999","data":[3]},{"name":"22-JUL-1997","data":[2]},{"name":"22-JUN-1998","data":[1]},{"name":"22-MAR-1999","data":[3]},{"name":"22-MAY-1997","data":[2]},{"name":"22-MAY-1998","data":[1]},{"name":"22-NOV-1996","data":[3]},{"name":"22-NOV-1999","data":[1]},{"name":"22-OCT-1996","data":[1]},{"name":"22-OCT-1998","data":[4]},{"name":"22-SEP-1997","data":[1]},{"name":"22-SEP-1998","data":[2]},{"name":"23-APR-1997","data":[4]},{"name":"23-APR-1998","data":[2]},{"name":"23-APR-1999","data":[1]},{"name":"23-AUG-1997","data":[1]},{"name":"23-AUG-1999","data":[2]},{"name":"23-DEC-1998","data":[3]},{"name":"23-FEB-1999","data":[4]},{"name":"23-FEB-2000","data":[2]},{"name":"23-JAN-1997","data":[1]},{"name":"23-JAN-1998","data":[4]},{"name":"23-JUL-1997","data":[2]},{"name":"23-JUL-1998","data":[1]},{"name":"23-JUN-1997","data":[4]},{"name":"23-JUN-1998","data":[2]},{"name":"23-MAR-1998","data":[9]},{"name":"23-MAR-1999","data":[2]},{"name":"23-MAR-2000","data":[1]},{"name":"23-MAY-1997","data":[6]},{"name":"23-NOV-1998","data":[1]},{"name":"23-OCT-1997","data":[5]},{"name":"23-SEP-1997","data":[3]},{"name":"23-SEP-1998","data":[4]},{"name":"23-SEP-1999","data":[1]},{"name":"24-APR-1998","data":[1]},{"name":"24-AUG-1998","data":[3]},{"name":"24-AUG-1999","data":[1]},{"name":"24-FEB-1998","data":[3]},{"name":"24-FEB-1999","data":[4]},{"name":"24-FEB-2000","data":[3]},{"name":"24-JAN-1998","data":[1]},{"name":"24-JUL-1997","data":[6]},{"name":"24-JUL-1998","data":[2]},{"name":"24-JUN-1997","data":[6]},{"name":"24-JUN-1998","data":[3]},{"name":"24-MAR-1997","data":[9]},{"name":"24-MAR-1998","data":[1]},{"name":"24-MAR-1999","data":[7]},{"name":"24-MAY-1999","data":[1]},{"name":"24-NOV-1997","data":[3]},{"name":"24-OCT-1997","data":[1]},{"name":"24-SEP-1996","data":[3]},{"name":"24-SEP-1997","data":[5]},{"name":"24-SEP-1998","data":[5]},{"name":"25-APR-1997","data":[3]},{"name":"25-AUG-1997","data":[3]},{"name":"25-AUG-1999","data":[4]},{"name":"25-FEB-1998","data":[4]},{"name":"25-FEB-1999","data":[4]},{"name":"25-FEB-2000","data":[1]},{"name":"25-JAN-1999","data":[4]},{"name":"25-JUL-1997","data":[6]},{"name":"25-JUN-1997","data":[4]},{"name":"25-JUN-1998","data":[3]},{"name":"25-JUN-1999","data":[2]},{"name":"25-MAR-1998","data":[3]},{"name":"25-MAR-1999","data":[3]},{"name":"25-NOV-1996","data":[9]},{"name":"25-NOV-1997","data":[2]},{"name":"25-NOV-1998","data":[2]},{"name":"25-SEP-1998","data":[2]},{"name":"26-APR-1999","data":[2]},{"name":"26-AUG-1997","data":[4]},{"name":"26-AUG-1999","data":[4]},{"name":"26-FEB-1998","data":[2]},{"name":"26-FEB-1999","data":[3]},{"name":"26-JAN-1998","data":[2]},{"name":"26-JAN-1999","data":[1]},{"name":"26-JUL-1999","data":[1]},{"name":"26-JUN-1997","data":[5]},{"name":"26-JUN-1998","data":[4]},{"name":"26-MAR-1997","data":[3]},{"name":"26-MAR-1998","data":[4]},{"name":"26-MAR-1999","data":[2]},{"name":"26-MAY-1997","data":[4]},{"name":"26-MAY-1998","data":[2]},{"name":"26-MAY-1999","data":[2]},{"name":"26-NOV-1996","data":[7]},{"name":"26-NOV-1997","data":[6]},{"name":"26-OCT-1998","data":[4]},{"name":"26-SEP-1997","data":[1]},{"name":"27-APR-1998","data":[4]},{"name":"27-APR-1999","data":[1]},{"name":"27-AUG-1997","data":[4]},{"name":"27-AUG-1998","data":[1]},{"name":"27-AUG-1999","data":[1]},{"name":"27-DEC-1996","data":[2]},{"name":"27-FEB-1997","data":[1]},{"name":"27-FEB-1998","data":[4]},{"name":"27-FEB-1999","data":[2]},{"name":"27-JAN-1998","data":[1]},{"name":"27-JAN-2000","data":[1]},{"name":"27-JUN-1997","data":[3]},{"name":"27-MAR-1997","data":[6]},{"name":"27-MAR-1998","data":[2]},{"name":"27-MAY-1997","data":[5]},{"name":"27-MAY-1998","data":[3]},{"name":"27-MAY-1999","data":[2]},{"name":"27-OCT-1999","data":[4]},{"name":"28-APR-1998","data":[6]},{"name":"28-APR-1999","data":[2]},{"name":"28-AUG-1997","data":[1]},{"name":"28-AUG-1998","data":[1]},{"name":"28-FEB-1999","data":[1]},{"name":"28-FEB-2000","data":[1]},{"name":"28-JAN-1998","data":[3]},{"name":"28-JAN-1999","data":[1]},{"name":"28-JUL-1997","data":[2]},{"name":"28-JUL-1998","data":[6]},{"name":"28-MAY-1997","data":[4]},{"name":"28-MAY-1998","data":[1]},{"name":"28-OCT-1996","data":[2]},{"name":"28-OCT-1997","data":[2]},{"name":"28-OCT-1998","data":[1]},{"name":"28-SEP-1998","data":[2]},{"name":"29-APR-1997","data":[2]},{"name":"29-APR-1998","data":[1]},{"name":"29-APR-1999","data":[1]},{"name":"29-AUG-1997","data":[2]},{"name":"29-DEC-1996","data":[2]},{"name":"29-DEC-1997","data":[5]},{"name":"29-DEC-1998","data":[2]},{"name":"29-JAN-1997","data":[5]},{"name":"29-JAN-1998","data":[5]},{"name":"29-JAN-1999","data":[2]},{"name":"29-JUL-1997","data":[1]},{"name":"29-JUL-1998","data":[4]},{"name":"29-JUL-1999","data":[1]},{"name":"29-JUN-1998","data":[3]},{"name":"29-JUN-1999","data":[2]},{"name":"29-MAR-1998","data":[1]},{"name":"29-MAR-1999","data":[3]},{"name":"29-MAY-1997","data":[1]},{"name":"29-OCT-1996","data":[1]},{"name":"29-OCT-1997","data":[6]},{"name":"29-OCT-1998","data":[5]},{"name":"29-SEP-1997","data":[6]},{"name":"29-SEP-1998","data":[1]},{"name":"30-APR-1997","data":[3]},{"name":"30-AUG-1997","data":[2]},{"name":"30-AUG-1998","data":[1]},{"name":"30-DEC-1996","data":[4]},{"name":"30-DEC-1997","data":[3]},{"name":"30-JAN-1997","data":[6]},{"name":"30-JAN-1998","data":[1]},{"name":"30-JUL-1997","data":[2]},{"name":"30-JUL-1998","data":[3]},{"name":"30-JUN-1997","data":[4]},{"name":"30-JUN-1998","data":[6]},{"name":"30-MAR-1998","data":[9]},{"name":"30-MAR-1999","data":[1]},{"name":"30-MAY-1997","data":[3]},{"name":"30-NOV-1998","data":[4]},{"name":"30-OCT-1997","data":[5]},{"name":"30-OCT-1998","data":[1]},{"name":"30-SEP-1996","data":[3]},{"name":"30-SEP-1997","data":[2]},{"name":"30-SEP-1998","data":[5]},{"name":"31-AUG-1998","data":[1]},{"name":"31-AUG-1999","data":[1]},{"name":"31-DEC-1997","data":[4]},{"name":"31-JAN-1998","data":[1]},{"name":"31-JAN-2000","data":[1]},{"name":"31-JUL-1997","data":[5]},{"name":"31-MAR-1997","data":[5]},{"name":"31-MAR-1998","data":[1]},{"name":"31-MAR-1999","data":[2]},{"name":"31-OCT-1997","data":[3]}]},{"ASCR":[{"name":"0","data":[68]},{"name":"1","data":[1962]}]},{"WHYNS":[{"name":"-2","data":[1962]},{"name":"ADMITTED TO NH","data":[1]},{"name":"ANGRY,SUSPICIOUS","data":[1]},{"name":"BLANKED","data":[1]},{"name":"CG JUST OUT OF HOSPITAL","data":[1]},{"name":"CR DECEASED","data":[2]},{"name":"CR DECEASED-FEB.1ST.","data":[1]},{"name":"CR DIED","data":[4]},{"name":"CR DOES NOT LIVE W/CG.","data":[1]},{"name":"CR INSTITUTIONALIZED","data":[1]},{"name":"CR JUST OUT OF HOSPITAL","data":[1]},{"name":"CR PLACED IN ASSISTED LIVG FAC","data":[1]},{"name":"CR PLACED IN NURSG HM 10/1/97","data":[1]},{"name":"CR TAKING NEW PILL-THINGS GOOD","data":[1]},{"name":"DEATH IN FAMILY","data":[1]},{"name":"DID NOT LIKE THE QUESTIONS","data":[1]},{"name":"DIDN'T HAVE TIME TO DEAL W/IT","data":[1]},{"name":"DOES NOT HAVE TIME","data":[2]},{"name":"DOES NOT HAVE TIME.","data":[1]},{"name":"DOESN'T THINK WILL BENEFIT HIM","data":[1]},{"name":"DOESN'T WANT TO KNOW MORE","data":[1]},{"name":"DON'T HAVE TIME TO WASTE","data":[1]},{"name":"DON'T WANT TO TRY ANYTHING NEW","data":[1]},{"name":"FOSTER CARE HOME","data":[1]},{"name":"HAS BROKEN LEG, FOOT","data":[1]},{"name":"INELG. CR MOVING","data":[1]},{"name":"INELIG NOT LIVING TOGETHER","data":[1]},{"name":"INTERESTED IN PLACING CR ASAP","data":[1]},{"name":"KNOW ALL ABOUT GERONTOLOGY","data":[1]},{"name":"MAY PARTICIPATE LATER","data":[1]},{"name":"NO TIME","data":[1]},{"name":"NOT INTERESTED","data":[5]},{"name":"NOT INTERESTED IN PROGRAM","data":[1]},{"name":"NOT INTERESTED IN STUDY","data":[2]},{"name":"NOT INTERESTED IN SUPPORT, WAN","data":[1]},{"name":"NOT INTERESTED NOW","data":[1]},{"name":"NOT INTERESTED.","data":[8]},{"name":"NOT RELATED TO CR","data":[1]},{"name":"PENDING C.B.","data":[1]},{"name":"PLACED MOTHER","data":[1]},{"name":"REFUSED","data":[1]},{"name":"TOO BUSY","data":[3]},{"name":"TOO BUSY WITH 2-YEAR-OLD.","data":[1]},{"name":"TOO OVERWHELMED","data":[1]},{"name":"TOO OVERWHELMED/DOESN'T GO DR.","data":[1]},{"name":"TOO SICK.","data":[1]},{"name":"UNABLE TO CONTACT","data":[1]},{"name":"WANTS MORE INFO","data":[1]},{"name":"WANTS TO WAIT","data":[1]},{"name":"WAS MOVING OUT OF TOWN","data":[1]}]},{"SCID":[{"name":"-2","data":[68]},{"name":"1020214","data":[2]},{"name":"1200004","data":[1]},{"name":"1200006","data":[1]},{"name":"1200007","data":[1]},{"name":"1200008","data":[1]},{"name":"1200009","data":[1]},{"name":"1200010","data":[1]},{"name":"1200011","data":[1]},{"name":"1200013","data":[1]},{"name":"1200014","data":[1]},{"name":"1200015","data":[1]},{"name":"1200016","data":[2]},{"name":"1200036","data":[2]},{"name":"1200038","data":[3]},{"name":"1200039","data":[1]},{"name":"1200040","data":[1]},{"name":"1200041","data":[1]},{"name":"1200042","data":[1]},{"name":"1200044","data":[1]},{"name":"1200045","data":[1]},{"name":"1200046","data":[1]},{"name":"1200047","data":[1]},{"name":"1200048","data":[1]},{"name":"1200050","data":[2]},{"name":"1200053","data":[1]},{"name":"1200054","data":[1]},{"name":"1200058","data":[1]},{"name":"1200060","data":[1]},{"name":"1200061","data":[1]},{"name":"1200062","data":[1]},{"name":"1200065","data":[1]},{"name":"1200067","data":[1]},{"name":"1200081","data":[1]},{"name":"1200085","data":[2]},{"name":"1200102","data":[1]},{"name":"1200103","data":[1]},{"name":"1200133","data":[1]},{"name":"1200140","data":[1]},{"name":"1200155","data":[1]},{"name":"1200156","data":[1]},{"name":"1200159","data":[1]},{"name":"1200161","data":[1]},{"name":"1200164","data":[2]},{"name":"1200171","data":[1]},{"name":"1200184","data":[2]},{"name":"1200186","data":[2]},{"name":"1200302","data":[1]},{"name":"1210018","data":[1]},{"name":"1210019","data":[1]},{"name":"1210020","data":[1]},{"name":"1210023","data":[3]},{"name":"1210024","data":[1]},{"name":"1210025","data":[2]},{"name":"1210026","data":[1]},{"name":"1210027","data":[1]},{"name":"1210028","data":[1]},{"name":"1210029","data":[2]},{"name":"1210031","data":[2]},{"name":"1210032","data":[1]},{"name":"1210033","data":[1]},{"name":"1210034","data":[1]},{"name":"1210035","data":[1]},{"name":"1210037","data":[2]},{"name":"1210049","data":[2]},{"name":"1210051","data":[1]},{"name":"1210052","data":[1]},{"name":"1210055","data":[2]},{"name":"1210056","data":[1]},{"name":"1210057","data":[1]},{"name":"1210059","data":[1]},{"name":"1210063","data":[1]},{"name":"1210064","data":[1]},{"name":"1210066","data":[1]},{"name":"1210068","data":[1]},{"name":"1210069","data":[1]},{"name":"1210070","data":[1]},{"name":"1210071","data":[2]},{"name":"1210072","data":[1]},{"name":"1210073","data":[1]},{"name":"1210075","data":[1]},{"name":"1210076","data":[1]},{"name":"1210079","data":[1]},{"name":"1210080","data":[1]},{"name":"1210082","data":[2]},{"name":"1210083","data":[2]},{"name":"1210084","data":[1]},{"name":"1210092","data":[1]},{"name":"1210093","data":[1]},{"name":"1210095","data":[1]},{"name":"1210096","data":[1]},{"name":"1210097","data":[1]},{"name":"1210098","data":[1]},{"name":"1210099","data":[1]},{"name":"1210100","data":[1]},{"name":"1210101","data":[1]},{"name":"1210105","data":[1]},{"name":"1210108","data":[1]},{"name":"1210119","data":[1]},{"name":"1210134","data":[2]},{"name":"1210136","data":[1]},{"name":"1210138","data":[1]},{"name":"1210142","data":[1]},{"name":"1210145","data":[1]},{"name":"1210153","data":[1]},{"name":"1210154","data":[1]},{"name":"1210157","data":[1]},{"name":"1210158","data":[1]},{"name":"1210165","data":[1]},{"name":"1210166","data":[1]},{"name":"1210170","data":[1]},{"name":"1210181","data":[1]},{"name":"1210199","data":[1]},{"name":"1210206","data":[1]},{"name":"1210243","data":[1]},{"name":"1210249","data":[1]},{"name":"1220074","data":[2]},{"name":"1220078","data":[1]},{"name":"1220089","data":[2]},{"name":"1220090","data":[1]},{"name":"1220091","data":[2]},{"name":"1220109","data":[1]},{"name":"1220115","data":[2]},{"name":"1220182","data":[1]},{"name":"1220185","data":[1]},{"name":"1220219","data":[1]},{"name":"1230012","data":[1]},{"name":"1230017","data":[1]},{"name":"1230043","data":[1]},{"name":"1230086","data":[4]},{"name":"1230087","data":[1]},{"name":"1230088","data":[2]},{"name":"1230094","data":[1]},{"name":"1230111","data":[2]},{"name":"1230118","data":[1]},{"name":"1230143","data":[1]},{"name":"1230160","data":[1]},{"name":"1230168","data":[1]},{"name":"1240005","data":[1]},{"name":"1240021","data":[1]},{"name":"1240022","data":[1]},{"name":"1240030","data":[2]},{"name":"1240077","data":[1]},{"name":"1240104","data":[1]},{"name":"1240106","data":[1]},{"name":"1240107","data":[2]},{"name":"1240110","data":[1]},{"name":"1240112","data":[2]},{"name":"1240113","data":[1]},{"name":"1240114","data":[2]},{"name":"1240116","data":[1]},{"name":"1240117","data":[1]},{"name":"1240121","data":[1]},{"name":"1240122","data":[1]},{"name":"1240123","data":[1]},{"name":"1240124","data":[1]},{"name":"1240125","data":[2]},{"name":"1240126","data":[2]},{"name":"1240127","data":[1]},{"name":"1240128","data":[1]},{"name":"1240129","data":[1]},{"name":"1240130","data":[1]},{"name":"1240131","data":[1]},{"name":"1240132","data":[1]},{"name":"1240135","data":[2]},{"name":"1240137","data":[2]},{"name":"1240139","data":[1]},{"name":"1240141","data":[1]},{"name":"1240144","data":[1]},{"name":"1240147","data":[1]},{"name":"1240148","data":[1]},{"name":"1240149","data":[1]},{"name":"1240150","data":[2]},{"name":"1240151","data":[2]},{"name":"1240162","data":[1]},{"name":"1240163","data":[1]},{"name":"1240168","data":[2]},{"name":"1240169","data":[2]},{"name":"1240172","data":[1]},{"name":"1240173","data":[1]},{"name":"1240174","data":[1]},{"name":"1240175","data":[1]},{"name":"1240176","data":[1]},{"name":"1240177","data":[1]},{"name":"1240178","data":[2]},{"name":"1240179","data":[1]},{"name":"1240180","data":[1]},{"name":"1240183","data":[1]},{"name":"1240187","data":[1]},{"name":"1240188","data":[1]},{"name":"1240190","data":[2]},{"name":"1240191","data":[2]},{"name":"1240192","data":[1]},{"name":"1240193","data":[1]},{"name":"1240194","data":[1]},{"name":"1240195","data":[1]},{"name":"1240196","data":[1]},{"name":"1240198","data":[1]},{"name":"1240201","data":[1]},{"name":"1240203","data":[1]},{"name":"1240205","data":[1]},{"name":"1240207","data":[1]},{"name":"1240208","data":[1]},{"name":"1240210","data":[1]},{"name":"1240211","data":[1]},{"name":"1240212","data":[1]},{"name":"1240213","data":[1]},{"name":"1240215","data":[1]},{"name":"1240216","data":[1]},{"name":"1240217","data":[1]},{"name":"1240218","data":[1]},{"name":"1240220","data":[1]},{"name":"1240221","data":[1]},{"name":"1240222","data":[1]},{"name":"1240223","data":[1]},{"name":"1240224","data":[1]},{"name":"1240225","data":[2]},{"name":"1240226","data":[1]},{"name":"1240227","data":[1]},{"name":"1240228","data":[1]},{"name":"1240229","data":[1]},{"name":"1240230","data":[1]},{"name":"1240231","data":[1]},{"name":"1240232","data":[2]},{"name":"1240235","data":[2]},{"name":"1240236","data":[2]},{"name":"1240237","data":[2]},{"name":"1240238","data":[2]},{"name":"1240239","data":[2]},{"name":"1240241","data":[1]},{"name":"1240242","data":[2]},{"name":"1240244","data":[1]},{"name":"1240245","data":[2]},{"name":"1240246","data":[1]},{"name":"1240247","data":[2]},{"name":"1240248","data":[1]},{"name":"1240250","data":[1]},{"name":"1240251","data":[1]},{"name":"1240252","data":[1]},{"name":"1240254","data":[1]},{"name":"1240255","data":[1]},{"name":"1240256","data":[1]},{"name":"1240257","data":[1]},{"name":"1240258","data":[2]},{"name":"1240259","data":[2]},{"name":"1240260","data":[2]},{"name":"1240261","data":[1]},{"name":"1240262","data":[2]},{"name":"1240263","data":[2]},{"name":"1240264","data":[2]},{"name":"1240265","data":[1]},{"name":"1240266","data":[2]},{"name":"1240268","data":[2]},{"name":"1240269","data":[2]},{"name":"1240270","data":[1]},{"name":"1240272","data":[1]},{"name":"1240273","data":[1]},{"name":"1240274","data":[1]},{"name":"1240275","data":[1]},{"name":"1240276","data":[1]},{"name":"1240277","data":[1]},{"name":"1240278","data":[1]},{"name":"1240280","data":[2]},{"name":"1240281","data":[1]},{"name":"1240282","data":[1]},{"name":"1240283","data":[1]},{"name":"1240285","data":[1]},{"name":"1240286","data":[1]},{"name":"1240287","data":[1]},{"name":"1240288","data":[1]},{"name":"1240289","data":[1]},{"name":"1240290","data":[1]},{"name":"1240291","data":[1]},{"name":"1240292","data":[1]},{"name":"1240293","data":[1]},{"name":"1240294","data":[1]},{"name":"1240295","data":[1]},{"name":"1240296","data":[1]},{"name":"1240297","data":[1]},{"name":"1240298","data":[1]},{"name":"1240299","data":[1]},{"name":"1240300","data":[1]},{"name":"1240301","data":[1]},{"name":"1240303","data":[1]},{"name":"1240304","data":[1]},{"name":"1240305","data":[1]},{"name":"1250146","data":[2]},{"name":"1250152","data":[2]},{"name":"1250234","data":[1]},{"name":"1250271","data":[1]},{"name":"1250279","data":[1]},{"name":"2100001","data":[1]},{"name":"2100002","data":[1]},{"name":"2100003","data":[1]},{"name":"2100004","data":[1]},{"name":"2100005","data":[1]},{"name":"2100006","data":[1]},{"name":"2100007","data":[1]},{"name":"2100008","data":[1]},{"name":"2100009","data":[1]},{"name":"2100010","data":[1]},{"name":"2100011","data":[1]},{"name":"2100012","data":[1]},{"name":"2100013","data":[1]},{"name":"2100014","data":[1]},{"name":"2100020","data":[1]},{"name":"2100021","data":[1]},{"name":"2100023","data":[1]},{"name":"2100025","data":[1]},{"name":"2100026","data":[1]},{"name":"2100027","data":[1]},{"name":"2100031","data":[1]},{"name":"2100034","data":[1]},{"name":"2100039","data":[1]},{"name":"2100040","data":[1]},{"name":"2100042","data":[1]},{"name":"2100043","data":[1]},{"name":"2100044","data":[1]},{"name":"2100047","data":[1]},{"name":"2100050","data":[1]},{"name":"2100068","data":[1]},{"name":"2110089","data":[1]},{"name":"2110111","data":[1]},{"name":"2110114","data":[1]},{"name":"2110115","data":[1]},{"name":"2120049","data":[1]},{"name":"2120066","data":[1]},{"name":"2120077","data":[1]},{"name":"2120083","data":[1]},{"name":"2120090","data":[1]},{"name":"2120091","data":[1]},{"name":"2120098","data":[1]},{"name":"2130056","data":[1]},{"name":"2130061","data":[1]},{"name":"2130062","data":[1]},{"name":"2130063","data":[1]},{"name":"2130088","data":[1]},{"name":"2140015","data":[1]},{"name":"2140016","data":[1]},{"name":"2140017","data":[1]},{"name":"2140018","data":[1]},{"name":"2140019","data":[1]},{"name":"2140022","data":[1]},{"name":"2140024","data":[1]},{"name":"2140028","data":[1]},{"name":"2140030","data":[1]},{"name":"2140032","data":[1]},{"name":"2140033","data":[1]},{"name":"2140035","data":[1]},{"name":"2140036","data":[1]},{"name":"2140037","data":[1]},{"name":"2140038","data":[1]},{"name":"2140041","data":[1]},{"name":"2140045","data":[1]},{"name":"2140046","data":[1]},{"name":"2140048","data":[1]},{"name":"2140051","data":[1]},{"name":"2140052","data":[1]},{"name":"2140053","data":[1]},{"name":"2140054","data":[1]},{"name":"2140055","data":[1]},{"name":"2140057","data":[1]},{"name":"2140058","data":[1]},{"name":"2140059","data":[1]},{"name":"2140060","data":[1]},{"name":"2140064","data":[1]},{"name":"2140065","data":[1]},{"name":"2140073","data":[1]},{"name":"2150121","data":[1]},{"name":"2150122","data":[1]},{"name":"2150124","data":[1]},{"name":"2160067","data":[1]},{"name":"2170079","data":[1]},{"name":"2170080","data":[1]},{"name":"2170085","data":[1]},{"name":"2170087","data":[1]},{"name":"2170093","data":[1]},{"name":"2180069","data":[1]},{"name":"2180071","data":[1]},{"name":"2180072","data":[1]},{"name":"2180075","data":[1]},{"name":"2180076","data":[1]},{"name":"2180078","data":[1]},{"name":"2180082","data":[1]},{"name":"2180086","data":[1]},{"name":"2190070","data":[1]},{"name":"2190074","data":[1]},{"name":"2190081","data":[1]},{"name":"2190084","data":[1]},{"name":"2190092","data":[1]},{"name":"2190094","data":[1]},{"name":"2190095","data":[1]},{"name":"2190096","data":[1]},{"name":"2190097","data":[1]},{"name":"2190099","data":[1]},{"name":"2190100","data":[1]},{"name":"2190101","data":[1]},{"name":"2190102","data":[1]},{"name":"2190103","data":[1]},{"name":"2190104","data":[1]},{"name":"2190105","data":[1]},{"name":"2190106","data":[1]},{"name":"2190107","data":[1]},{"name":"2190108","data":[1]},{"name":"2190109","data":[1]},{"name":"2190110","data":[1]},{"name":"2190112","data":[1]},{"name":"2190113","data":[1]},{"name":"2190118","data":[1]},{"name":"2190119","data":[1]},{"name":"2190120","data":[1]},{"name":"2190125","data":[1]},{"name":"2190126","data":[1]},{"name":"2190127","data":[1]},{"name":"2190128","data":[1]},{"name":"2190129","data":[1]},{"name":"2190130","data":[1]},{"name":"2190131","data":[1]},{"name":"2190132","data":[1]},{"name":"3010002","data":[1]},{"name":"3010006","data":[1]},{"name":"3010007","data":[1]},{"name":"3010008","data":[1]},{"name":"3010009","data":[1]},{"name":"3010010","data":[1]},{"name":"3010011","data":[1]},{"name":"3010012","data":[1]},{"name":"3010013","data":[1]},{"name":"3010014","data":[1]},{"name":"3010015","data":[1]},{"name":"3010016","data":[1]},{"name":"3010017","data":[1]},{"name":"3010019","data":[1]},{"name":"3010020","data":[1]},{"name":"3010021","data":[1]},{"name":"3010022","data":[1]},{"name":"3010023","data":[1]},{"name":"3010024","data":[1]},{"name":"3010025","data":[1]},{"name":"3010026","data":[1]},{"name":"3010027","data":[1]},{"name":"3010028","data":[1]},{"name":"3010029","data":[1]},{"name":"3010030","data":[1]},{"name":"3010041","data":[1]},{"name":"3010046","data":[1]},{"name":"3010047","data":[1]},{"name":"3010048","data":[1]},{"name":"3010055","data":[1]},{"name":"3010065","data":[1]},{"name":"3010091","data":[1]},{"name":"3010202","data":[1]},{"name":"3010311","data":[1]},{"name":"3010345","data":[1]},{"name":"3010361","data":[1]},{"name":"3020104","data":[1]},{"name":"3020105","data":[1]},{"name":"3020114","data":[1]},{"name":"3020115","data":[1]},{"name":"3020144","data":[1]},{"name":"3020149","data":[1]},{"name":"3020153","data":[1]},{"name":"3020158","data":[1]},{"name":"3020179","data":[1]},{"name":"3020186","data":[1]},{"name":"3020188","data":[1]},{"name":"3020189","data":[1]},{"name":"3020203","data":[1]},{"name":"3020207","data":[1]},{"name":"3020223","data":[1]},{"name":"3020227","data":[1]},{"name":"3020239","data":[1]},{"name":"3020255","data":[1]},{"name":"3020257","data":[1]},{"name":"3020272","data":[1]},{"name":"3020310","data":[1]},{"name":"3020350","data":[1]},{"name":"3020371","data":[1]},{"name":"3020379","data":[1]},{"name":"3020384","data":[1]},{"name":"3020425","data":[1]},{"name":"3030031","data":[1]},{"name":"3030032","data":[1]},{"name":"3030034","data":[1]},{"name":"3030035","data":[1]},{"name":"3030037","data":[1]},{"name":"3030038","data":[1]},{"name":"3030039","data":[1]},{"name":"3030040","data":[1]},{"name":"3030042","data":[1]},{"name":"3030043","data":[1]},{"name":"3030044","data":[1]},{"name":"3030045","data":[1]},{"name":"3030049","data":[1]},{"name":"3030050","data":[1]},{"name":"3030051","data":[1]},{"name":"3030052","data":[1]},{"name":"3030053","data":[1]},{"name":"3030054","data":[1]},{"name":"3030056","data":[1]},{"name":"3030057","data":[1]},{"name":"3030058","data":[1]},{"name":"3030059","data":[1]},{"name":"3030060","data":[1]},{"name":"3030061","data":[1]},{"name":"3030062","data":[1]},{"name":"3030063","data":[1]},{"name":"3030064","data":[1]},{"name":"3030066","data":[1]},{"name":"3030067","data":[1]},{"name":"3030068","data":[1]},{"name":"3030070","data":[1]},{"name":"3030071","data":[1]},{"name":"3030072","data":[1]},{"name":"3030073","data":[1]},{"name":"3030074","data":[1]},{"name":"3030076","data":[1]},{"name":"3030079","data":[1]},{"name":"3030089","data":[1]},{"name":"3030101","data":[1]},{"name":"3030109","data":[1]},{"name":"3030110","data":[1]},{"name":"3030111","data":[1]},{"name":"3030112","data":[1]},{"name":"3030113","data":[1]},{"name":"3030117","data":[1]},{"name":"3030123","data":[1]},{"name":"3030124","data":[1]},{"name":"3030125","data":[1]},{"name":"3030129","data":[1]},{"name":"3030132","data":[1]},{"name":"3030133","data":[1]},{"name":"3030137","data":[1]},{"name":"3030142","data":[1]},{"name":"3030145","data":[1]},{"name":"3030146","data":[1]},{"name":"3030150","data":[1]},{"name":"3030155","data":[1]},{"name":"3030157","data":[1]},{"name":"3030191","data":[1]},{"name":"3030192","data":[1]},{"name":"3030193","data":[1]},{"name":"3030197","data":[1]},{"name":"3030198","data":[1]},{"name":"3030204","data":[1]},{"name":"3030205","data":[1]},{"name":"3030206","data":[1]},{"name":"3030208","data":[1]},{"name":"3030209","data":[1]},{"name":"3030213","data":[1]},{"name":"3030224","data":[1]},{"name":"3030228","data":[1]},{"name":"3030236","data":[1]},{"name":"3030241","data":[1]},{"name":"3030243","data":[1]},{"name":"3030245","data":[1]},{"name":"3030248","data":[1]},{"name":"3030254","data":[1]},{"name":"3030269","data":[1]},{"name":"3030278","data":[1]},{"name":"3030281","data":[1]},{"name":"3030295","data":[1]},{"name":"3030296","data":[1]},{"name":"3030314","data":[1]},{"name":"3030320","data":[1]},{"name":"3030326","data":[1]},{"name":"3030334","data":[1]},{"name":"3030347","data":[1]},{"name":"3030348","data":[1]},{"name":"3030351","data":[1]},{"name":"3030353","data":[1]},{"name":"3030364","data":[1]},{"name":"3030367","data":[1]},{"name":"3030402","data":[1]},{"name":"3030413","data":[1]},{"name":"3030435","data":[1]},{"name":"3030438","data":[1]},{"name":"3030440","data":[1]},{"name":"3040001","data":[1]},{"name":"3040003","data":[1]},{"name":"3040018","data":[1]},{"name":"3040033","data":[1]},{"name":"3040036","data":[1]},{"name":"3040069","data":[1]},{"name":"3040075","data":[1]},{"name":"3040102","data":[1]},{"name":"3040106","data":[1]},{"name":"3040108","data":[1]},{"name":"3040119","data":[1]},{"name":"3040121","data":[1]},{"name":"3040122","data":[1]},{"name":"3040128","data":[1]},{"name":"3040143","data":[1]},{"name":"3040147","data":[1]},{"name":"3040167","data":[1]},{"name":"3040181","data":[1]},{"name":"3040185","data":[1]},{"name":"3040210","data":[1]},{"name":"3040225","data":[1]},{"name":"3040230","data":[1]},{"name":"3040264","data":[1]},{"name":"3040271","data":[1]},{"name":"3040308","data":[1]},{"name":"3040321","data":[1]},{"name":"3040323","data":[1]},{"name":"3040339","data":[1]},{"name":"3040343","data":[1]},{"name":"3040352","data":[1]},{"name":"3040366","data":[1]},{"name":"3040373","data":[1]},{"name":"3040378","data":[1]},{"name":"3040397","data":[1]},{"name":"3040403","data":[1]},{"name":"3040423","data":[1]},{"name":"3040431","data":[1]},{"name":"3050077","data":[1]},{"name":"3050078","data":[1]},{"name":"3050080","data":[1]},{"name":"3050081","data":[1]},{"name":"3050082","data":[1]},{"name":"3050083","data":[1]},{"name":"3050084","data":[1]},{"name":"3050085","data":[1]},{"name":"3050086","data":[1]},{"name":"3050087","data":[1]},{"name":"3050088","data":[1]},{"name":"3050090","data":[1]},{"name":"3050092","data":[1]},{"name":"3050093","data":[1]},{"name":"3050094","data":[1]},{"name":"3050095","data":[1]},{"name":"3050096","data":[1]},{"name":"3050097","data":[1]},{"name":"3050098","data":[1]},{"name":"3050100","data":[1]},{"name":"3050103","data":[1]},{"name":"3050107","data":[1]},{"name":"3050116","data":[1]},{"name":"3050118","data":[1]},{"name":"3050120","data":[1]},{"name":"3050126","data":[1]},{"name":"3050127","data":[1]},{"name":"3050130","data":[1]},{"name":"3050131","data":[1]},{"name":"3050134","data":[1]},{"name":"3050135","data":[1]},{"name":"3050136","data":[1]},{"name":"3050138","data":[1]},{"name":"3050139","data":[1]},{"name":"3050140","data":[1]},{"name":"3050141","data":[1]},{"name":"3050148","data":[1]},{"name":"3050151","data":[1]},{"name":"3050152","data":[1]},{"name":"3050154","data":[1]},{"name":"3050156","data":[1]},{"name":"3050159","data":[1]},{"name":"3050160","data":[1]},{"name":"3050161","data":[1]},{"name":"3050162","data":[1]},{"name":"3050163","data":[1]},{"name":"3050164","data":[1]},{"name":"3050165","data":[1]},{"name":"3050166","data":[1]},{"name":"3050168","data":[1]},{"name":"3050169","data":[1]},{"name":"3050170","data":[1]},{"name":"3050171","data":[1]},{"name":"3050172","data":[1]},{"name":"3050173","data":[1]},{"name":"3050174","data":[1]},{"name":"3050175","data":[1]},{"name":"3050176","data":[1]},{"name":"3050177","data":[1]},{"name":"3050178","data":[1]},{"name":"3050180","data":[1]},{"name":"3050182","data":[1]},{"name":"3050183","data":[1]},{"name":"3050184","data":[1]},{"name":"3050187","data":[1]},{"name":"3050190","data":[1]},{"name":"3050194","data":[1]},{"name":"3050195","data":[1]},{"name":"3050196","data":[1]},{"name":"3050199","data":[1]},{"name":"3050200","data":[1]},{"name":"3050201","data":[1]},{"name":"3050211","data":[1]},{"name":"3050212","data":[1]},{"name":"3050214","data":[1]},{"name":"3050215","data":[1]},{"name":"3050216","data":[1]},{"name":"3050217","data":[1]},{"name":"3050218","data":[1]},{"name":"3050219","data":[1]},{"name":"3050220","data":[1]},{"name":"3050221","data":[1]},{"name":"3050222","data":[1]},{"name":"3050226","data":[1]},{"name":"3050229","data":[1]},{"name":"3050231","data":[1]},{"name":"3050233","data":[1]},{"name":"3050234","data":[1]},{"name":"3050235","data":[1]},{"name":"3050237","data":[1]},{"name":"3050238","data":[1]},{"name":"3050240","data":[1]},{"name":"3050242","data":[1]},{"name":"3050244","data":[1]},{"name":"3050246","data":[1]},{"name":"3050247","data":[1]},{"name":"3050249","data":[1]},{"name":"3050250","data":[1]},{"name":"3050251","data":[1]},{"name":"3050252","data":[1]},{"name":"3050253","data":[1]},{"name":"3050256","data":[1]},{"name":"3050258","data":[1]},{"name":"3050259","data":[1]},{"name":"3050260","data":[1]},{"name":"3050261","data":[1]},{"name":"3050262","data":[1]},{"name":"3050263","data":[1]},{"name":"3050265","data":[1]},{"name":"3050266","data":[1]},{"name":"3050267","data":[1]},{"name":"3050268","data":[1]},{"name":"3050270","data":[1]},{"name":"3050273","data":[1]},{"name":"3050274","data":[1]},{"name":"3050275","data":[1]},{"name":"3050276","data":[1]},{"name":"3050277","data":[1]},{"name":"3050279","data":[1]},{"name":"3050280","data":[1]},{"name":"3050282","data":[1]},{"name":"3050283","data":[1]},{"name":"3050284","data":[1]},{"name":"3050285","data":[1]},{"name":"3050286","data":[1]},{"name":"3050287","data":[1]},{"name":"3050288","data":[1]},{"name":"3050289","data":[1]},{"name":"3050290","data":[1]},{"name":"3050291","data":[1]},{"name":"3050292","data":[1]},{"name":"3050293","data":[1]},{"name":"3050294","data":[1]},{"name":"3050297","data":[1]},{"name":"3050298","data":[1]},{"name":"3050299","data":[1]},{"name":"3050300","data":[1]},{"name":"3050301","data":[1]},{"name":"3050302","data":[1]},{"name":"3050304","data":[1]},{"name":"3050305","data":[1]},{"name":"3050306","data":[1]},{"name":"3050307","data":[1]},{"name":"3050309","data":[1]},{"name":"3050312","data":[1]},{"name":"3050313","data":[1]},{"name":"3050315","data":[1]},{"name":"3050316","data":[1]},{"name":"3050317","data":[1]},{"name":"3050318","data":[1]},{"name":"3050319","data":[1]},{"name":"3050322","data":[1]},{"name":"3050324","data":[1]},{"name":"3050327","data":[1]},{"name":"3050328","data":[1]},{"name":"3050329","data":[1]},{"name":"3050330","data":[1]},{"name":"3050331","data":[1]},{"name":"3050332","data":[1]},{"name":"3050333","data":[1]},{"name":"3050335","data":[1]},{"name":"3050336","data":[1]},{"name":"3050337","data":[1]},{"name":"3050338","data":[1]},{"name":"3050340","data":[1]},{"name":"3050341","data":[1]},{"name":"3050342","data":[1]},{"name":"3050344","data":[1]},{"name":"3050346","data":[1]},{"name":"3050349","data":[1]},{"name":"3050354","data":[1]},{"name":"3050355","data":[1]},{"name":"3050356","data":[1]},{"name":"3050357","data":[1]},{"name":"3050358","data":[1]},{"name":"3050359","data":[1]},{"name":"3050360","data":[1]},{"name":"3050362","data":[1]},{"name":"3050363","data":[1]},{"name":"3050365","data":[1]},{"name":"3050368","data":[1]},{"name":"3050369","data":[1]},{"name":"3050370","data":[1]},{"name":"3050372","data":[1]},{"name":"3050374","data":[1]},{"name":"3050375","data":[1]},{"name":"3050376","data":[1]},{"name":"3050377","data":[1]},{"name":"3050380","data":[1]},{"name":"3050381","data":[1]},{"name":"3050382","data":[1]},{"name":"3050383","data":[1]},{"name":"3050385","data":[1]},{"name":"3050386","data":[1]},{"name":"3050387","data":[1]},{"name":"3050388","data":[1]},{"name":"3050389","data":[1]},{"name":"3050390","data":[1]},{"name":"3050391","data":[1]},{"name":"3050392","data":[1]},{"name":"3050393","data":[1]},{"name":"3050394","data":[1]},{"name":"3050395","data":[1]},{"name":"3050396","data":[1]},{"name":"3050398","data":[1]},{"name":"3050399","data":[1]},{"name":"3050400","data":[1]},{"name":"3050401","data":[1]},{"name":"3050404","data":[1]},{"name":"3050405","data":[1]},{"name":"3050406","data":[1]},{"name":"3050407","data":[1]},{"name":"3050408","data":[1]},{"name":"3050409","data":[1]},{"name":"3050410","data":[1]},{"name":"3050411","data":[1]},{"name":"3050412","data":[1]},{"name":"3050414","data":[1]},{"name":"3050415","data":[1]},{"name":"3050416","data":[1]},{"name":"3050417","data":[1]},{"name":"3050418","data":[1]},{"name":"3050419","data":[1]},{"name":"3050420","data":[1]},{"name":"3050421","data":[1]},{"name":"3050422","data":[1]},{"name":"3050424","data":[1]},{"name":"3050426","data":[1]},{"name":"3050427","data":[1]},{"name":"3050428","data":[1]},{"name":"3050429","data":[1]},{"name":"3050430","data":[1]},{"name":"3050432","data":[1]},{"name":"3050433","data":[1]},{"name":"3050434","data":[1]},{"name":"3050436","data":[1]},{"name":"3050437","data":[1]},{"name":"3050439","data":[1]},{"name":"3050441","data":[1]},{"name":"4300001","data":[1]},{"name":"4300002","data":[1]},{"name":"4300003","data":[1]},{"name":"4300004","data":[1]},{"name":"4300006","data":[1]},{"name":"4300007","data":[1]},{"name":"4300008","data":[1]},{"name":"4300015","data":[1]},{"name":"4300017","data":[1]},{"name":"4300018","data":[1]},{"name":"4300019","data":[1]},{"name":"4300020","data":[1]},{"name":"4300021","data":[1]},{"name":"4300022","data":[1]},{"name":"4300023","data":[1]},{"name":"4300024","data":[1]},{"name":"4300026","data":[1]},{"name":"4300027","data":[1]},{"name":"4300028","data":[1]},{"name":"4300029","data":[1]},{"name":"4300032","data":[1]},{"name":"4300033","data":[1]},{"name":"4300035","data":[1]},{"name":"4300036","data":[1]},{"name":"4300037","data":[1]},{"name":"4300038","data":[1]},{"name":"4300039","data":[1]},{"name":"4300042","data":[1]},{"name":"4300043","data":[1]},{"name":"4300044","data":[1]},{"name":"4300045","data":[1]},{"name":"4300046","data":[1]},{"name":"4300047","data":[1]},{"name":"4300048","data":[1]},{"name":"4300049","data":[1]},{"name":"4300050","data":[1]},{"name":"4300051","data":[1]},{"name":"4300052","data":[1]},{"name":"4300053","data":[1]},{"name":"4300054","data":[1]},{"name":"4300058","data":[1]},{"name":"4300065","data":[1]},{"name":"4300066","data":[1]},{"name":"4300067","data":[1]},{"name":"4300068","data":[1]},{"name":"4300071","data":[1]},{"name":"4300072","data":[1]},{"name":"4300073","data":[1]},{"name":"4300077","data":[1]},{"name":"4300078","data":[1]},{"name":"4300079","data":[1]},{"name":"4300082","data":[1]},{"name":"4300084","data":[1]},{"name":"4300086","data":[1]},{"name":"4300091","data":[1]},{"name":"4300094","data":[1]},{"name":"4300101","data":[1]},{"name":"4300135","data":[1]},{"name":"4300144","data":[1]},{"name":"4300145","data":[1]},{"name":"4300147","data":[1]},{"name":"4300148","data":[1]},{"name":"4300149","data":[1]},{"name":"4300150","data":[1]},{"name":"4300151","data":[1]},{"name":"4300152","data":[1]},{"name":"4300153","data":[1]},{"name":"4300155","data":[1]},{"name":"4300164","data":[1]},{"name":"4300168","data":[1]},{"name":"4300173","data":[1]},{"name":"4300177","data":[1]},{"name":"4300184","data":[1]},{"name":"4300202","data":[1]},{"name":"4300217","data":[1]},{"name":"4300219","data":[1]},{"name":"4300237","data":[1]},{"name":"4300243","data":[1]},{"name":"4300245","data":[1]},{"name":"4300250","data":[1]},{"name":"4300251","data":[1]},{"name":"4300252","data":[1]},{"name":"4300256","data":[1]},{"name":"4300270","data":[1]},{"name":"4300271","data":[1]},{"name":"4300283","data":[1]},{"name":"4300290","data":[1]},{"name":"4300296","data":[1]},{"name":"4300301","data":[1]},{"name":"4300308","data":[1]},{"name":"4310005","data":[1]},{"name":"4310009","data":[1]},{"name":"4310010","data":[1]},{"name":"4310011","data":[1]},{"name":"4310012","data":[1]},{"name":"4310016","data":[1]},{"name":"4310030","data":[1]},{"name":"4310031","data":[1]},{"name":"4310034","data":[1]},{"name":"4310040","data":[1]},{"name":"4310057","data":[1]},{"name":"4310059","data":[1]},{"name":"4310064","data":[1]},{"name":"4310083","data":[1]},{"name":"4310097","data":[1]},{"name":"4310125","data":[1]},{"name":"4310165","data":[1]},{"name":"4310166","data":[1]},{"name":"4310169","data":[1]},{"name":"4310170","data":[1]},{"name":"4310172","data":[1]},{"name":"4310174","data":[1]},{"name":"4310183","data":[1]},{"name":"4310213","data":[1]},{"name":"4310284","data":[1]},{"name":"4310306","data":[1]},{"name":"4320055","data":[1]},{"name":"4320056","data":[1]},{"name":"4320060","data":[1]},{"name":"4320061","data":[1]},{"name":"4320062","data":[1]},{"name":"4320063","data":[1]},{"name":"4320069","data":[1]},{"name":"4320070","data":[1]},{"name":"4320075","data":[1]},{"name":"4320076","data":[1]},{"name":"4320080","data":[1]},{"name":"4320081","data":[1]},{"name":"4320085","data":[1]},{"name":"4320087","data":[1]},{"name":"4320088","data":[1]},{"name":"4320090","data":[1]},{"name":"4320092","data":[1]},{"name":"4320095","data":[1]},{"name":"4320096","data":[1]},{"name":"4320098","data":[1]},{"name":"4320099","data":[1]},{"name":"4320100","data":[1]},{"name":"4320102","data":[1]},{"name":"4320103","data":[1]},{"name":"4320104","data":[1]},{"name":"4320105","data":[1]},{"name":"4320106","data":[1]},{"name":"4320107","data":[1]},{"name":"4320108","data":[1]},{"name":"4320109","data":[1]},{"name":"4320110","data":[1]},{"name":"4320111","data":[1]},{"name":"4320112","data":[1]},{"name":"4320113","data":[1]},{"name":"4320114","data":[1]},{"name":"4320115","data":[1]},{"name":"4320116","data":[1]},{"name":"4320117","data":[1]},{"name":"4320118","data":[1]},{"name":"4320119","data":[1]},{"name":"4320120","data":[1]},{"name":"4320121","data":[1]},{"name":"4320122","data":[1]},{"name":"4320123","data":[1]},{"name":"4320124","data":[1]},{"name":"4320126","data":[1]},{"name":"4320127","data":[1]},{"name":"4320128","data":[1]},{"name":"4320129","data":[1]},{"name":"4320130","data":[1]},{"name":"4320131","data":[1]},{"name":"4320132","data":[1]},{"name":"4320133","data":[1]},{"name":"4320134","data":[1]},{"name":"4320136","data":[1]},{"name":"4320137","data":[1]},{"name":"4320138","data":[1]},{"name":"4320139","data":[1]},{"name":"4320140","data":[1]},{"name":"4320141","data":[1]},{"name":"4320142","data":[1]},{"name":"4320146","data":[1]},{"name":"4320154","data":[1]},{"name":"4320156","data":[1]},{"name":"4320157","data":[1]},{"name":"4320158","data":[1]},{"name":"4320159","data":[1]},{"name":"4320160","data":[1]},{"name":"4320161","data":[1]},{"name":"4320162","data":[1]},{"name":"4320163","data":[1]},{"name":"4320167","data":[1]},{"name":"4320171","data":[1]},{"name":"4320175","data":[1]},{"name":"4320176","data":[1]},{"name":"4320178","data":[1]},{"name":"4320179","data":[1]},{"name":"4320180","data":[1]},{"name":"4320181","data":[1]},{"name":"4320182","data":[1]},{"name":"4320186","data":[1]},{"name":"4320187","data":[1]},{"name":"4320188","data":[1]},{"name":"4320189","data":[1]},{"name":"4320190","data":[1]},{"name":"4320191","data":[1]},{"name":"4320192","data":[1]},{"name":"4320193","data":[1]},{"name":"4320194","data":[1]},{"name":"4320195","data":[1]},{"name":"4320196","data":[1]},{"name":"4320197","data":[1]},{"name":"4320198","data":[1]},{"name":"4320199","data":[1]},{"name":"4320200","data":[1]},{"name":"4320201","data":[1]},{"name":"4320203","data":[1]},{"name":"4320204","data":[1]},{"name":"4320205","data":[1]},{"name":"4320206","data":[1]},{"name":"4320207","data":[1]},{"name":"4320208","data":[1]},{"name":"4320209","data":[1]},{"name":"4320210","data":[1]},{"name":"4320211","data":[1]},{"name":"4320212","data":[1]},{"name":"4320214","data":[1]},{"name":"4320215","data":[1]},{"name":"4320216","data":[1]},{"name":"4320218","data":[1]},{"name":"4320220","data":[1]},{"name":"4320221","data":[1]},{"name":"4320222","data":[1]},{"name":"4320223","data":[1]},{"name":"4320224","data":[1]},{"name":"4320225","data":[1]},{"name":"4320226","data":[1]},{"name":"4320227","data":[1]},{"name":"4320228","data":[1]},{"name":"4320229","data":[1]},{"name":"4320230","data":[1]},{"name":"4320231","data":[1]},{"name":"4320232","data":[1]},{"name":"4320233","data":[1]},{"name":"4320234","data":[1]},{"name":"4320235","data":[1]},{"name":"4320236","data":[1]},{"name":"4320238","data":[1]},{"name":"4320239","data":[1]},{"name":"4320240","data":[1]},{"name":"4320241","data":[1]},{"name":"4320242","data":[1]},{"name":"4320244","data":[1]},{"name":"4320246","data":[1]},{"name":"4320247","data":[1]},{"name":"4320248","data":[1]},{"name":"4320249","data":[1]},{"name":"4320253","data":[1]},{"name":"4320254","data":[1]},{"name":"4320255","data":[1]},{"name":"4320257","data":[1]},{"name":"4320258","data":[1]},{"name":"4320259","data":[1]},{"name":"4320260","data":[1]},{"name":"4320261","data":[1]},{"name":"4320262","data":[1]},{"name":"4320263","data":[1]},{"name":"4320264","data":[1]},{"name":"4320265","data":[1]},{"name":"4320266","data":[1]},{"name":"4320267","data":[1]},{"name":"4320268","data":[1]},{"name":"4320269","data":[1]},{"name":"4320273","data":[1]},{"name":"4320274","data":[1]},{"name":"4320275","data":[1]},{"name":"4320276","data":[1]},{"name":"4320277","data":[1]},{"name":"4320278","data":[1]},{"name":"4320279","data":[1]},{"name":"4320280","data":[1]},{"name":"4320281","data":[1]},{"name":"4320282","data":[1]},{"name":"4320285","data":[1]},{"name":"4320286","data":[1]},{"name":"4320287","data":[1]},{"name":"4320288","data":[1]},{"name":"4320289","data":[1]},{"name":"4320291","data":[1]},{"name":"4320292","data":[1]},{"name":"4320293","data":[1]},{"name":"4320294","data":[1]},{"name":"4320295","data":[1]},{"name":"4320297","data":[1]},{"name":"4320298","data":[1]},{"name":"4320299","data":[1]},{"name":"4320300","data":[1]},{"name":"4320302","data":[1]},{"name":"4320303","data":[1]},{"name":"4320304","data":[1]},{"name":"4320305","data":[1]},{"name":"4320307","data":[1]},{"name":"5400232","data":[1]},{"name":"5400233","data":[1]},{"name":"5410071","data":[1]},{"name":"5410148","data":[1]},{"name":"5410188","data":[1]},{"name":"5410202","data":[1]},{"name":"5420327","data":[1]},{"name":"5430011","data":[1]},{"name":"5430012","data":[1]},{"name":"5430030","data":[1]},{"name":"5430033","data":[1]},{"name":"5430044","data":[1]},{"name":"5430050","data":[1]},{"name":"5430053","data":[1]},{"name":"5430057","data":[1]},{"name":"5430058","data":[1]},{"name":"5430070","data":[1]},{"name":"5430080","data":[1]},{"name":"5430083","data":[1]},{"name":"5430091","data":[1]},{"name":"5430147","data":[1]},{"name":"5430183","data":[1]},{"name":"5430197","data":[1]},{"name":"5430201","data":[1]},{"name":"5430214","data":[1]},{"name":"5430220","data":[1]},{"name":"5430222","data":[1]},{"name":"5430308","data":[1]},{"name":"5430311","data":[1]},{"name":"5430318","data":[1]},{"name":"5430336","data":[1]},{"name":"5430341","data":[1]},{"name":"5440006","data":[1]},{"name":"5440007","data":[1]},{"name":"5440010","data":[1]},{"name":"5440019","data":[1]},{"name":"5440025","data":[1]},{"name":"5440031","data":[1]},{"name":"5440041","data":[1]},{"name":"5440045","data":[1]},{"name":"5440046","data":[1]},{"name":"5440047","data":[1]},{"name":"5440048","data":[1]},{"name":"5440049","data":[1]},{"name":"5440051","data":[1]},{"name":"5440052","data":[1]},{"name":"5440054","data":[1]},{"name":"5440065","data":[1]},{"name":"5440079","data":[1]},{"name":"5440089","data":[1]},{"name":"5440090","data":[1]},{"name":"5440150","data":[1]},{"name":"5440151","data":[1]},{"name":"5440155","data":[1]},{"name":"5440162","data":[1]},{"name":"5440163","data":[1]},{"name":"5440168","data":[1]},{"name":"5440169","data":[1]},{"name":"5440193","data":[1]},{"name":"5440206","data":[1]},{"name":"5440210","data":[1]},{"name":"5440219","data":[1]},{"name":"5440223","data":[1]},{"name":"5440247","data":[1]},{"name":"5440265","data":[1]},{"name":"5440266","data":[1]},{"name":"5440310","data":[1]},{"name":"5440331","data":[1]},{"name":"5440332","data":[1]},{"name":"5440337","data":[1]},{"name":"5440338","data":[1]},{"name":"5440355","data":[1]},{"name":"5440359","data":[1]},{"name":"5450008","data":[1]},{"name":"5450016","data":[1]},{"name":"5450017","data":[1]},{"name":"5450018","data":[1]},{"name":"5450024","data":[1]},{"name":"5450026","data":[1]},{"name":"5450027","data":[1]},{"name":"5450028","data":[1]},{"name":"5450032","data":[1]},{"name":"5450115","data":[1]},{"name":"5450182","data":[1]},{"name":"5450192","data":[1]},{"name":"5450195","data":[1]},{"name":"5450224","data":[1]},{"name":"5450255","data":[1]},{"name":"5450258","data":[1]},{"name":"5450275","data":[1]},{"name":"5450276","data":[1]},{"name":"5450330","data":[1]},{"name":"5450352","data":[1]},{"name":"5460001","data":[1]},{"name":"5460043","data":[1]},{"name":"5460095","data":[1]},{"name":"5460098","data":[1]},{"name":"5460125","data":[1]},{"name":"5460170","data":[1]},{"name":"5460198","data":[1]},{"name":"5460225","data":[1]},{"name":"5460238","data":[1]},{"name":"5460239","data":[1]},{"name":"5460240","data":[1]},{"name":"5460248","data":[1]},{"name":"5460250","data":[1]},{"name":"5460258","data":[1]},{"name":"5460262","data":[1]},{"name":"5460270","data":[1]},{"name":"5460274","data":[1]},{"name":"5460279","data":[1]},{"name":"5460289","data":[1]},{"name":"5460350","data":[1]},{"name":"5460356","data":[1]},{"name":"5470092","data":[1]},{"name":"5470100","data":[1]},{"name":"5470101","data":[1]},{"name":"5470114","data":[1]},{"name":"5470124","data":[1]},{"name":"5470136","data":[1]},{"name":"5470137","data":[1]},{"name":"5470144","data":[1]},{"name":"5470185","data":[1]},{"name":"5470187","data":[1]},{"name":"5470189","data":[1]},{"name":"5470190","data":[1]},{"name":"5470194","data":[1]},{"name":"5470199","data":[1]},{"name":"5470200","data":[1]},{"name":"5470209","data":[1]},{"name":"5470241","data":[1]},{"name":"5470268","data":[1]},{"name":"5470272","data":[1]},{"name":"5470285","data":[1]},{"name":"5470323","data":[1]},{"name":"5470340","data":[1]},{"name":"5480164","data":[1]},{"name":"5480178","data":[2]},{"name":"5480179","data":[1]},{"name":"5480221","data":[1]},{"name":"5480249","data":[1]},{"name":"5480251","data":[1]},{"name":"5480263","data":[1]},{"name":"5480264","data":[1]},{"name":"5480267","data":[1]},{"name":"5480328","data":[1]},{"name":"5480339","data":[1]},{"name":"5480342","data":[1]},{"name":"5480344","data":[1]},{"name":"5480354","data":[1]},{"name":"5480360","data":[1]},{"name":"5490039","data":[1]},{"name":"5490055","data":[1]},{"name":"5490056","data":[1]},{"name":"5490059","data":[1]},{"name":"5490060","data":[1]},{"name":"5490061","data":[1]},{"name":"5490062","data":[1]},{"name":"5490063","data":[1]},{"name":"5490064","data":[1]},{"name":"5490066","data":[1]},{"name":"5490067","data":[1]},{"name":"5490068","data":[1]},{"name":"5490073","data":[1]},{"name":"5490074","data":[1]},{"name":"5490075","data":[1]},{"name":"5490076","data":[1]},{"name":"5490077","data":[1]},{"name":"5490078","data":[1]},{"name":"5490081","data":[1]},{"name":"5490084","data":[1]},{"name":"5490085","data":[1]},{"name":"5490086","data":[1]},{"name":"5490087","data":[1]},{"name":"5490088","data":[1]},{"name":"5490094","data":[1]},{"name":"5490096","data":[1]},{"name":"5490127","data":[1]},{"name":"5490128","data":[1]},{"name":"5490129","data":[1]},{"name":"5490130","data":[1]},{"name":"5490138","data":[1]},{"name":"5490139","data":[1]},{"name":"5490145","data":[1]},{"name":"5490152","data":[1]},{"name":"5490165","data":[1]},{"name":"5490166","data":[1]},{"name":"5490184","data":[1]},{"name":"5490205","data":[1]},{"name":"5490207","data":[1]},{"name":"5490208","data":[1]},{"name":"5490211","data":[1]},{"name":"5490212","data":[1]},{"name":"5490216","data":[1]},{"name":"5490217","data":[1]},{"name":"5490218","data":[1]},{"name":"5490252","data":[1]},{"name":"5490254","data":[1]},{"name":"5490269","data":[1]},{"name":"5490271","data":[1]},{"name":"5490273","data":[1]},{"name":"5490277","data":[1]},{"name":"5490278","data":[1]},{"name":"5490280","data":[1]},{"name":"5490281","data":[1]},{"name":"5490282","data":[1]},{"name":"5490283","data":[1]},{"name":"5490284","data":[1]},{"name":"5490286","data":[1]},{"name":"5490287","data":[1]},{"name":"5490288","data":[1]},{"name":"5490290","data":[1]},{"name":"5490291","data":[1]},{"name":"5490292","data":[1]},{"name":"5490293","data":[1]},{"name":"5490294","data":[1]},{"name":"5490295","data":[1]},{"name":"5490296","data":[1]},{"name":"5490325","data":[1]},{"name":"5490326","data":[1]},{"name":"5490333","data":[1]},{"name":"5490348","data":[1]},{"name":"5490349","data":[1]},{"name":"5490353","data":[1]},{"name":"5490357","data":[1]},{"name":"5490361","data":[1]},{"name":"5490362","data":[1]},{"name":"5490363","data":[1]},{"name":"5500014","data":[1]},{"name":"5500035","data":[1]},{"name":"5500040","data":[1]},{"name":"5500082","data":[1]},{"name":"5500117","data":[1]},{"name":"5500118","data":[1]},{"name":"5500120","data":[1]},{"name":"5500146","data":[1]},{"name":"5500167","data":[1]},{"name":"5500171","data":[1]},{"name":"5500172","data":[1]},{"name":"5500186","data":[1]},{"name":"5500253","data":[1]},{"name":"5500259","data":[1]},{"name":"5500260","data":[1]},{"name":"5510072","data":[1]},{"name":"5510156","data":[1]},{"name":"5510157","data":[1]},{"name":"5510158","data":[1]},{"name":"5510159","data":[1]},{"name":"5510160","data":[1]},{"name":"5510161","data":[1]},{"name":"5510176","data":[1]},{"name":"5510177","data":[1]},{"name":"5510180","data":[1]},{"name":"5510181","data":[1]},{"name":"5510191","data":[1]},{"name":"5510196","data":[1]},{"name":"5510229","data":[1]},{"name":"5510236","data":[1]},{"name":"5510237","data":[1]},{"name":"5510242","data":[1]},{"name":"5510243","data":[1]},{"name":"5510244","data":[1]},{"name":"5510245","data":[1]},{"name":"5510256","data":[1]},{"name":"5510257","data":[1]},{"name":"5510297","data":[1]},{"name":"5510298","data":[1]},{"name":"5510299","data":[1]},{"name":"5510300","data":[1]},{"name":"5510301","data":[1]},{"name":"5510302","data":[1]},{"name":"5510303","data":[1]},{"name":"5510304","data":[1]},{"name":"5510305","data":[1]},{"name":"5510306","data":[1]},{"name":"5510307","data":[1]},{"name":"5520004","data":[1]},{"name":"5520005","data":[1]},{"name":"5520097","data":[1]},{"name":"5520102","data":[1]},{"name":"5520103","data":[1]},{"name":"5520112","data":[1]},{"name":"5520113","data":[1]},{"name":"5520116","data":[1]},{"name":"5520119","data":[1]},{"name":"5520121","data":[1]},{"name":"5520123","data":[1]},{"name":"5520126","data":[1]},{"name":"5520131","data":[1]},{"name":"5520149","data":[1]},{"name":"5520173","data":[1]},{"name":"5520174","data":[1]},{"name":"5520175","data":[1]},{"name":"5520203","data":[1]},{"name":"5520204","data":[1]},{"name":"5530002","data":[1]},{"name":"5530003","data":[1]},{"name":"5530029","data":[1]},{"name":"5540099","data":[1]},{"name":"5540104","data":[1]},{"name":"5540105","data":[1]},{"name":"5540106","data":[1]},{"name":"5540107","data":[1]},{"name":"5540108","data":[1]},{"name":"5540109","data":[1]},{"name":"5540111","data":[1]},{"name":"5540132","data":[1]},{"name":"5540133","data":[1]},{"name":"5540134","data":[1]},{"name":"5540135","data":[1]},{"name":"5540140","data":[1]},{"name":"5540141","data":[1]},{"name":"5540143","data":[1]},{"name":"5540154","data":[1]},{"name":"5590034","data":[1]},{"name":"5590037","data":[1]},{"name":"5590153","data":[1]},{"name":"5590215","data":[1]},{"name":"5590226","data":[1]},{"name":"5590227","data":[1]},{"name":"5590228","data":[1]},{"name":"5590230","data":[1]},{"name":"5590231","data":[1]},{"name":"5590234","data":[1]},{"name":"5590235","data":[1]},{"name":"5590246","data":[1]},{"name":"5590261","data":[1]},{"name":"5590309","data":[1]},{"name":"5590312","data":[1]},{"name":"5590313","data":[1]},{"name":"5590314","data":[1]},{"name":"5590315","data":[1]},{"name":"5590316","data":[1]},{"name":"5590317","data":[1]},{"name":"5590320","data":[1]},{"name":"5590321","data":[1]},{"name":"5590322","data":[1]},{"name":"5590324","data":[1]},{"name":"5590329","data":[1]},{"name":"5590334","data":[1]},{"name":"5590335","data":[1]},{"name":"5590343","data":[1]},{"name":"5590345","data":[1]},{"name":"5590346","data":[1]},{"name":"5590347","data":[1]},{"name":"5590351","data":[1]},{"name":"5590358","data":[1]},{"name":"5590364","data":[1]},{"name":"5590365","data":[1]},{"name":"5590366","data":[1]},{"name":"6600001","data":[1]},{"name":"6600002","data":[1]},{"name":"6600003","data":[1]},{"name":"6600004","data":[1]},{"name":"6600005","data":[1]},{"name":"6600006","data":[1]},{"name":"6600008","data":[1]},{"name":"6600009","data":[1]},{"name":"6600010","data":[1]},{"name":"6600011","data":[1]},{"name":"6600012","data":[1]},{"name":"6600013","data":[1]},{"name":"6600014","data":[1]},{"name":"6600015","data":[1]},{"name":"6600016","data":[1]},{"name":"6600018","data":[1]},{"name":"6600019","data":[1]},{"name":"6600020","data":[1]},{"name":"6600021","data":[1]},{"name":"6600022","data":[1]},{"name":"6600023","data":[1]},{"name":"6600024","data":[1]},{"name":"6600027","data":[1]},{"name":"6600029","data":[1]},{"name":"6600030","data":[1]},{"name":"6600031","data":[1]},{"name":"6600033","data":[1]},{"name":"6600036","data":[1]},{"name":"6600038","data":[1]},{"name":"6600045","data":[1]},{"name":"6600046","data":[1]},{"name":"6600048","data":[1]},{"name":"6600054","data":[1]},{"name":"6600055","data":[1]},{"name":"6600056","data":[1]},{"name":"6600057","data":[1]},{"name":"6600062","data":[1]},{"name":"6600066","data":[1]},{"name":"6600068","data":[1]},{"name":"6600072","data":[1]},{"name":"6600073","data":[1]},{"name":"6600082","data":[1]},{"name":"6600086","data":[1]},{"name":"6600088","data":[1]},{"name":"6600089","data":[1]},{"name":"6600090","data":[1]},{"name":"6600091","data":[1]},{"name":"6600093","data":[1]},{"name":"6600097","data":[1]},{"name":"6600098","data":[1]},{"name":"6600099","data":[1]},{"name":"6600100","data":[1]},{"name":"6600103","data":[1]},{"name":"6600105","data":[1]},{"name":"6600106","data":[1]},{"name":"6600107","data":[1]},{"name":"6600108","data":[1]},{"name":"6600109","data":[1]},{"name":"6600110","data":[1]},{"name":"6600111","data":[1]},{"name":"6600112","data":[1]},{"name":"6600113","data":[1]},{"name":"6600114","data":[1]},{"name":"6600115","data":[1]},{"name":"6600119","data":[1]},{"name":"6600121","data":[1]},{"name":"6600122","data":[1]},{"name":"6600129","data":[1]},{"name":"6600131","data":[1]},{"name":"6600133","data":[1]},{"name":"6600138","data":[1]},{"name":"6600141","data":[1]},{"name":"6600146","data":[1]},{"name":"6600148","data":[1]},{"name":"6600149","data":[1]},{"name":"6600150","data":[1]},{"name":"6600151","data":[1]},{"name":"6600152","data":[1]},{"name":"6600155","data":[1]},{"name":"6600156","data":[1]},{"name":"6600159","data":[1]},{"name":"6600160","data":[1]},{"name":"6600166","data":[1]},{"name":"6600167","data":[1]},{"name":"6600168","data":[1]},{"name":"6600169","data":[1]},{"name":"6600171","data":[1]},{"name":"6600172","data":[1]},{"name":"6600173","data":[1]},{"name":"6600177","data":[1]},{"name":"6600180","data":[1]},{"name":"6600181","data":[1]},{"name":"6600182","data":[1]},{"name":"6600183","data":[1]},{"name":"6600184","data":[1]},{"name":"6600185","data":[1]},{"name":"6600186","data":[1]},{"name":"6600188","data":[1]},{"name":"6600189","data":[1]},{"name":"6600190","data":[1]},{"name":"6600192","data":[1]},{"name":"6600193","data":[1]},{"name":"6600194","data":[1]},{"name":"6600195","data":[1]},{"name":"6600196","data":[1]},{"name":"6600197","data":[1]},{"name":"6600198","data":[1]},{"name":"6600199","data":[1]},{"name":"6600200","data":[1]},{"name":"6600201","data":[1]},{"name":"6600202","data":[1]},{"name":"6600203","data":[1]},{"name":"6600204","data":[1]},{"name":"6600205","data":[1]},{"name":"6600207","data":[1]},{"name":"6600210","data":[1]},{"name":"6600211","data":[1]},{"name":"6600212","data":[1]},{"name":"6600213","data":[1]},{"name":"6600214","data":[1]},{"name":"6600215","data":[1]},{"name":"6600217","data":[1]},{"name":"6600218","data":[1]},{"name":"6600219","data":[1]},{"name":"6600220","data":[1]},{"name":"6600221","data":[1]},{"name":"6600222","data":[1]},{"name":"6600223","data":[1]},{"name":"6600224","data":[1]},{"name":"6600225","data":[1]},{"name":"6600226","data":[1]},{"name":"6600227","data":[1]},{"name":"6600228","data":[1]},{"name":"6600229","data":[1]},{"name":"6600230","data":[1]},{"name":"6600232","data":[1]},{"name":"6600233","data":[1]},{"name":"6600234","data":[1]},{"name":"6600235","data":[1]},{"name":"6600236","data":[1]},{"name":"6600237","data":[1]},{"name":"6600238","data":[1]},{"name":"6600239","data":[1]},{"name":"6600240","data":[1]},{"name":"6600241","data":[1]},{"name":"6600242","data":[1]},{"name":"6600243","data":[1]},{"name":"6600244","data":[1]},{"name":"6600245","data":[1]},{"name":"6600246","data":[1]},{"name":"6600247","data":[1]},{"name":"6600248","data":[1]},{"name":"6600249","data":[1]},{"name":"6600250","data":[1]},{"name":"6600251","data":[1]},{"name":"6600252","data":[1]},{"name":"6600253","data":[1]},{"name":"6600254","data":[1]},{"name":"6600255","data":[1]},{"name":"6600256","data":[1]},{"name":"6600257","data":[1]},{"name":"6600259","data":[1]},{"name":"6600260","data":[1]},{"name":"6600263","data":[1]},{"name":"6600265","data":[1]},{"name":"6600271","data":[1]},{"name":"6600276","data":[1]},{"name":"6600285","data":[1]},{"name":"6600287","data":[1]},{"name":"6600290","data":[1]},{"name":"6600291","data":[1]},{"name":"6600292","data":[1]},{"name":"6600293","data":[1]},{"name":"6600295","data":[1]},{"name":"6600296","data":[1]},{"name":"6600299","data":[1]},{"name":"6600301","data":[1]},{"name":"6600303","data":[1]},{"name":"6600304","data":[1]},{"name":"6600305","data":[1]},{"name":"6600306","data":[1]},{"name":"6600307","data":[1]},{"name":"6600308","data":[1]},{"name":"6600309","data":[1]},{"name":"6600310","data":[1]},{"name":"6600311","data":[1]},{"name":"6600312","data":[1]},{"name":"6600313","data":[1]},{"name":"6600314","data":[1]},{"name":"6600315","data":[1]},{"name":"6600317","data":[1]},{"name":"6600319","data":[1]},{"name":"6600320","data":[1]},{"name":"6600323","data":[1]},{"name":"6600324","data":[1]},{"name":"6600325","data":[1]},{"name":"6600327","data":[1]},{"name":"6600328","data":[1]},{"name":"6600329","data":[1]},{"name":"6600330","data":[1]},{"name":"6600334","data":[1]},{"name":"6600335","data":[1]},{"name":"6600336","data":[1]},{"name":"6600337","data":[1]},{"name":"6600338","data":[1]},{"name":"6600339","data":[1]},{"name":"6600340","data":[1]},{"name":"6600341","data":[1]},{"name":"6600342","data":[1]},{"name":"6600343","data":[1]},{"name":"6600344","data":[1]},{"name":"6600345","data":[1]},{"name":"6600346","data":[1]},{"name":"6600347","data":[1]},{"name":"6600348","data":[1]},{"name":"6600349","data":[1]},{"name":"6600350","data":[1]},{"name":"6600351","data":[1]},{"name":"6600352","data":[1]},{"name":"6600353","data":[1]},{"name":"6600354","data":[1]},{"name":"6600355","data":[1]},{"name":"6600357","data":[1]},{"name":"6600358","data":[1]},{"name":"6600359","data":[1]},{"name":"6600360","data":[1]},{"name":"6600361","data":[1]},{"name":"6600362","data":[1]},{"name":"6600363","data":[1]},{"name":"6600368","data":[1]},{"name":"6600375","data":[1]},{"name":"6600377","data":[1]},{"name":"6600380","data":[1]},{"name":"6600381","data":[1]},{"name":"6600385","data":[1]},{"name":"6600386","data":[1]},{"name":"6600387","data":[1]},{"name":"6600391","data":[1]},{"name":"6600392","data":[1]},{"name":"6600395","data":[1]},{"name":"6600396","data":[1]},{"name":"6600398","data":[1]},{"name":"6600400","data":[1]},{"name":"6600401","data":[1]},{"name":"6610007","data":[1]},{"name":"6610028","data":[1]},{"name":"6610032","data":[1]},{"name":"6610034","data":[1]},{"name":"6610035","data":[1]},{"name":"6610037","data":[1]},{"name":"6610039","data":[1]},{"name":"6610040","data":[1]},{"name":"6610041","data":[1]},{"name":"6610042","data":[1]},{"name":"6610043","data":[1]},{"name":"6610044","data":[1]},{"name":"6610047","data":[1]},{"name":"6610049","data":[1]},{"name":"6610050","data":[1]},{"name":"6610051","data":[1]},{"name":"6610052","data":[1]},{"name":"6610053","data":[1]},{"name":"6610058","data":[1]},{"name":"6610059","data":[1]},{"name":"6610061","data":[1]},{"name":"6610064","data":[1]},{"name":"6610065","data":[1]},{"name":"6610067","data":[1]},{"name":"6610069","data":[1]},{"name":"6610071","data":[1]},{"name":"6610077","data":[1]},{"name":"6610078","data":[1]},{"name":"6610079","data":[1]},{"name":"6610080","data":[1]},{"name":"6610081","data":[1]},{"name":"6610083","data":[1]},{"name":"6610084","data":[1]},{"name":"6610085","data":[1]},{"name":"6610087","data":[1]},{"name":"6610092","data":[1]},{"name":"6610094","data":[1]},{"name":"6610095","data":[1]},{"name":"6610096","data":[1]},{"name":"6610101","data":[1]},{"name":"6610102","data":[1]},{"name":"6610104","data":[1]},{"name":"6610116","data":[1]},{"name":"6610117","data":[1]},{"name":"6610118","data":[1]},{"name":"6610120","data":[1]},{"name":"6610123","data":[1]},{"name":"6610124","data":[1]},{"name":"6610125","data":[1]},{"name":"6610126","data":[1]},{"name":"6610127","data":[1]},{"name":"6610128","data":[1]},{"name":"6610130","data":[1]},{"name":"6610132","data":[1]},{"name":"6610134","data":[1]},{"name":"6610135","data":[1]},{"name":"6610136","data":[1]},{"name":"6610137","data":[1]},{"name":"6610139","data":[1]},{"name":"6610140","data":[1]},{"name":"6610142","data":[1]},{"name":"6610143","data":[1]},{"name":"6610144","data":[1]},{"name":"6610145","data":[1]},{"name":"6610147","data":[1]},{"name":"6610153","data":[1]},{"name":"6610154","data":[1]},{"name":"6610157","data":[1]},{"name":"6610158","data":[1]},{"name":"6610161","data":[1]},{"name":"6610162","data":[1]},{"name":"6610163","data":[1]},{"name":"6610164","data":[1]},{"name":"6610165","data":[1]},{"name":"6610170","data":[1]},{"name":"6610174","data":[1]},{"name":"6610175","data":[1]},{"name":"6610176","data":[1]},{"name":"6610178","data":[1]},{"name":"6610179","data":[1]},{"name":"6610187","data":[1]},{"name":"6610191","data":[1]},{"name":"6610206","data":[1]},{"name":"6610208","data":[1]},{"name":"6610209","data":[1]},{"name":"6610216","data":[1]},{"name":"6610231","data":[1]},{"name":"6610258","data":[1]},{"name":"6610261","data":[1]},{"name":"6610262","data":[1]},{"name":"6610264","data":[1]},{"name":"6610266","data":[1]},{"name":"6610267","data":[1]},{"name":"6610268","data":[1]},{"name":"6610269","data":[1]},{"name":"6610270","data":[1]},{"name":"6610272","data":[1]},{"name":"6610273","data":[1]},{"name":"6610274","data":[1]},{"name":"6610275","data":[1]},{"name":"6610277","data":[1]},{"name":"6610278","data":[1]},{"name":"6610279","data":[1]},{"name":"6610280","data":[1]},{"name":"6610281","data":[1]},{"name":"6610282","data":[1]},{"name":"6610283","data":[1]},{"name":"6610284","data":[1]},{"name":"6610286","data":[1]},{"name":"6610288","data":[1]},{"name":"6610289","data":[1]},{"name":"6610294","data":[1]},{"name":"6610297","data":[1]},{"name":"6610298","data":[1]},{"name":"6610300","data":[1]},{"name":"6610302","data":[1]},{"name":"6610316","data":[1]},{"name":"6610318","data":[1]},{"name":"6610321","data":[1]},{"name":"6610322","data":[1]},{"name":"6610326","data":[1]},{"name":"6610331","data":[1]},{"name":"6610332","data":[1]},{"name":"6610333","data":[1]},{"name":"6610356","data":[1]},{"name":"6610364","data":[1]},{"name":"6610365","data":[1]},{"name":"6610366","data":[1]},{"name":"6610367","data":[1]},{"name":"6610369","data":[1]},{"name":"6610370","data":[1]},{"name":"6610371","data":[1]},{"name":"6610372","data":[1]},{"name":"6610373","data":[1]},{"name":"6610374","data":[1]},{"name":"6610376","data":[1]},{"name":"6610378","data":[1]},{"name":"6610379","data":[1]},{"name":"6610382","data":[1]},{"name":"6610383","data":[1]},{"name":"6610384","data":[1]},{"name":"6610388","data":[1]},{"name":"6610389","data":[1]},{"name":"6610390","data":[1]},{"name":"6610393","data":[1]},{"name":"6610394","data":[1]},{"name":"6610397","data":[1]},{"name":"6610399","data":[1]}]},{"ELIGI":[{"name":"-2","data":[69]},{"name":"0","data":[323]},{"name":"1","data":[1638]}]}]
